Workbook

Sheet B2026
A1: K EURO | E1: 2025 | Q1: 2025 | R1: 2026 | S1: 2027
E2: Jan | F2: Fev | G2: Mar | H2: Avr | I2: Mai | J2: Jui | K2: Juil | L2: Aou | M2: Sep | N2: Oct | O2: Nov | P2: Dec | Q2: Cumul fin Décembre | R2: Cumul fin Décembre | S2: Cumul fin Décembre
A3: PRODUIT | B3: PLAN_COMPTE | C3: TERRITOIRE | D3: CONSTRUCTEUR | E3: Budget | F3: Budget | G3: Budget | H3: Budget | I3: Budget | J3: Budget | K3: Budget | L3: Budget | M3: Budget | N3: Budget | O3: Budget | P3: Budget | Q3: Budget | R3: Plan N+1 | S3: Plan N+2
A4: Lift trucks | B4: Chiffre d'affaires | C4: Cameroun | D4: KALMAR | E4: 0 | F4: 571.68381 | G4: 0 | H4: 0 | I4: 815.60224 | J4: 0 | K4: 0 | L4: 815.60224 | M4: 0 | N4: 243.91843 | O4: 571.68381 | P4: 0 | Q4: 3018.4905 | R4: 3590.1744 | S4: 3917.9397
A5: Lift trucks | B5: Quantités facturées | C5: Cameroun | D5: KALMAR | E5: 0 | F5: 1 | G5: 0 | H5: 0 | I5: 2 | J5: 0 | K5: 0 | L5: 2 | M5: 0 | N5: 1 | O5: 1 | P5: 0 | Q5: 7 | R5: 0 | S5: 0
A6: Lift trucks | B6: Chiffre d'affaires | C6: Cameroun | D6: MANITOU | E6: 345.36274 | F6: 321.45209 | G6: 558.34997 | H6: 393.34431 | I6: 362.79081 | J6: 278.4086 | K6: 129.83758 | L6: 154.73516 | M6: 355.15982 | N6: 342.42479 | O6: 304.1858 | P6: 341.32307 | Q6: 3887.3747 | R6: 8359.324 | S6: 9255.7739
A7: Lift trucks | B7: Quantités facturées | C7: Cameroun | D7: MANITOU | E7: 2 | F7: 4 | G7: 5 | H7: 3 | I7: 3 | J7: 4 | K7: 0 | L7: 1 | M7: 6 | N7: 3 | O7: 2 | P7: 6 | Q7: 39 | R7: 29 | S7: 28
A8: Agricole | B8: Chiffre d'affaires | C8: Cameroun | D8: MASSEY FERGUSON | E8: 0 | F8: 328.52763 | G8: 32.776539 | H8: 32.776539 | I8: 92.231655 | J8: 32.776539 | K8: 0 | L8: 32.776539 | M8: 0 | N8: 32.776539 | O8: 32.776539 | P8: 92.231655 | Q8: 709.65018 | R8: 610.55831 | S8: 768.34305
A9: Agricole | B9: Quantités facturées | C9: Cameroun | D9: MASSEY FERGUSON | E9: 0 | F9: 4 | G9: 1 | H9: 1 | I9: 2 | J9: 1 | K9: 0 | L9: 1 | M9: 0 | N9: 1 | O9: 1 | P9: 2 | Q9: 14 | R9: 17 | S9: 21
A10: Agricole | B10: Chiffre d'affaires | C10: Cameroun | D10: NARDI | E10: 36.587764 | F10: 36.587764 | G10: 54.881646 | H10: 36.587764 | I10: 36.587764 | J10: 54.881646 | K10: 36.587764 | L10: 54.881646 | M10: 54.881646 | N10: 54.881646 | O10: 36.587764 | P10: 54.881646 | Q10: 548.81646 | R10: 212.9869 | S10: 243.4136
A11: Agricole | B11: Quantités facturées | C11: Cameroun | D11: NARDI | E11: 2 | F11: 2 | G11: 3 | H11: 2 | I11: 2 | J11: 3 | K11: 2 | L11: 3 | M11: 3 | N11: 3 | O11: 2 | P11: 3 | Q11: 30 | R11: 35 | S11: 40
A12: Lift trucks | B12: Chiffre d'affaires | C12: Congo | D12: KALMAR | E12: 191.841 | F12: 0 | G12: 0 | H12: 0 | I12: 0 | J12: 0 | K12: 0 | L12: 0 | M12: 0 | N12: 0 | O12: 0 | P12: 191.841 | Q12: 383.68201 | R12: 383.68201 | S12: 959.20502
A13: Lift trucks | B13: Quantités facturées | C13: Congo | D13: KALMAR | E13: 1 | F13: 0 | G13: 0 | H13: 0 | I13: 0 | J13: 0 | K13: 0 | L13: 0 | M13: 0 | N13: 0 | O13: 0 | P13: 1 | Q13: 2 | R13: 2 | S13: 5
A14: Lift trucks | B14: Chiffre d'affaires | C14: Congo | D14: MANITOU | E14: 32.04961 | F14: 165.09126 | G14: 141.51372 | H14: 34.260348 | I14: 55.43457 | J14: 34.260348 | K14: 34.260348 | L14: 87.48418 | M14: 32.04961 | N14: 70.756862 | O14: 130.35157 | P14: 32.04961 | Q14: 849.56204 | R14: 1411.0306 | S14: 1264.8774
A15: Lift trucks | B15: Quantités facturées | C15: Congo | D15: MANITOU | E15: 1 | F15: 2 | G15: 2 | H15: 1 | I15: 1 | J15: 1 | K15: 1 | L15: 2 | M15: 1 | N15: 1 | O15: 1 | P15: 1 | Q15: 15 | R15: 17 | S15: 16
... A95: Agricole | B95: Quantités facturées | C95: Total Territoire | D95: NARDI | E95: 10 | F95: 14 | G95: 18 | H95: 20 | I95: 18 | J95: 19 | K95: 18 | L95: 19 | M95: 18 | N95: 14 | O95: 16 | P95: 21 | Q95: 205 | R95: 251 | S95: 263

Sheet DRAFT - KPI's MANUTENTION ET AG
A1: PAYS | B1: YTD vs B2025 | E1: 45658 | H1: 45689 | K1: 45717 | N1: 45748 | Q1: 45778 | T1: 45809 | W1: 45839 | Z1: 45870 | AC1: 45901 | AF1: 45931 | AI1: 45962 | AL1: 45992
B2: Objectif | C2: Réalisé | D2: % | E2: Objectif | F2: Réalisé | G2: % | H2: Objectif | I2: Réalisé | J2: % | K2: Objectif | L2: Réalisé | M2: % | N2: Objectif | O2: Réalisé | P2: % | Q2: Objectif | R2: Réalisé | S2: % | T2: Objectif | U2: Réalisé | V2: % | W2: Objectif | X2: Réalisé | Y2: % | Z2: Objectif | AA2: Réalisé | AB2: % | AC2: Objectif | AD2: Réalisé | AE2: % | AF2: Objectif | AG2: Réalisé | AH2: % | AI2: Objectif | AJ2: Réalisé | AK2: % | AL2: Objectif | AM2: Réalisé | AN2: %
A3: Nombre de visites clients | B3: =+'KPI_VENDEUR 1'!B3+'KPI_VENDEUR 2'!B3+'KPI_VENDEUR 5'!B3+'KPI_VENDEUR 4'!B3+'KPI_VENDEUR 3'!B3 -> 0 | C3: =+'KPI_VENDEUR 1'!C3+'KPI_VENDEUR 2'!C3+'KPI_VENDEUR 5'!C3+'KPI_VENDEUR 4'!C3+'KPI_VENDEUR 3'!C3 -> 0 | D3: =C3/B3 -> #DIV/0! | E3: =+'KPI_VENDEUR 1'!E3+'KPI_VENDEUR 2'!E3+'KPI_VENDEUR 5'!E3+'KPI_VENDEUR 4'!E3+'KPI_VENDEUR 3'!E3 -> 0 | F3: =+'KPI_VENDEUR 1'!F3+'KPI_VENDEUR 2'!F3+'KPI_VENDEUR 5'!F3+'KPI_VENDEUR 4'!F3+'KPI_VENDEUR 3'!F3 -> 0 | G3: =F3/E3 -> #DIV/0! | H3: =+'KPI_VENDEUR 1'!H3+'KPI_VENDEUR 2'!H3+'KPI_VENDEUR 5'!H3+'KPI_VENDEUR 4'!H3+'KPI_VENDEUR 3'!H3 -> 0 | I3: =+'KPI_VENDEUR 1'!I3+'KPI_VENDEUR 2'!I3+'KPI_VENDEUR 5'!I3+'KPI_VENDEUR 4'!I3+'KPI_VENDEUR 3'!I3 -> 0 | J3: =I3/H3 -> #DIV/0! | K3: =+'KPI_VENDEUR 1'!K3+'KPI_VENDEUR 2'!K3+'KPI_VENDEUR 5'!K3+'KPI_VENDEUR 4'!K3+'KPI_VENDEUR 3'!K3 -> 0 | L3: =+'KPI_VENDEUR 1'!L3+'KPI_VENDEUR 2'!L3+'KPI_VENDEUR 5'!L3+'KPI_VENDEUR 4'!L3+'KPI_VENDEUR 3'!L3 -> 0 | M3: =L3/K3 -> #DIV/0! | N3: =+'KPI_VENDEUR 1'!N3+'KPI_VENDEUR 2'!N3+'KPI_VENDEUR 5'!N3+'KPI_VENDEUR 4'!N3+'KPI_VENDEUR 3'!N3 -> 0 | O3: =+'KPI_VENDEUR 1'!O3+'KPI_VENDEUR 2'!O3+'KPI_VENDEUR 5'!O3+'KPI_VENDEUR 4'!O3+'KPI_VENDEUR 3'!O3 -> 0 | P3: =O3/N3 -> #DIV/0! | Q3: =+'KPI_VENDEUR 1'!Q3+'KPI_VENDEUR 2'!Q3+'KPI_VENDEUR 5'!Q3+'KPI_VENDEUR 4'!Q3+'KPI_VENDEUR 3'!Q3 -> 0 | R3: =+'KPI_VENDEUR 1'!R3+'KPI_VENDEUR 2'!R3+'KPI_VENDEUR 5'!R3+'KPI_VENDEUR 4'!R3+'KPI_VENDEUR 3'!R3 -> 0 | S3: =R3/Q3 -> #DIV/0! | T3: =+'KPI_VENDEUR 1'!T3+'KPI_VENDEUR 2'!T3+'KPI_VENDEUR 5'!T3+'KPI_VENDEUR 4'!T3+'KPI_VENDEUR 3'!T3 -> 0 | U3: =+'KPI_VENDEUR 1'!U3+'KPI_VENDEUR 2'!U3+'KPI_VENDEUR 5'!U3+'KPI_VENDEUR 4'!U3+'KPI_VENDEUR 3'!U3 -> 0 | V3: =U3/T3 -> #DIV/0! | W3: =+'KPI_VENDEUR 1'!W3+'KPI_VENDEUR 2'!W3+'KPI_VENDEUR 5'!W3+'KPI_VENDEUR 4'!W3+'KPI_VENDEUR 3'!W3 -> 0 | X3: =+'KPI_VENDEUR 1'!X3+'KPI_VENDEUR 2'!X3+'KPI_VENDEUR 5'!X3+'KPI_VENDEUR 4'!X3+'KPI_VENDEUR 3'!X3 -> 0 | Y3: =X3/W3 -> #DIV/0! | Z3: =+'KPI_VENDEUR 1'!Z3+'KPI_VENDEUR 2'!Z3+'KPI_VENDEUR 5'!Z3+'KPI_VENDEUR 4'!Z3+'KPI_VENDEUR 3'!Z3 -> 0 | AA3: =+'KPI_VENDEUR 1'!AA3+'KPI_VENDEUR 2'!AA3+'KPI_VENDEUR 5'!AA3+'KPI_VENDEUR 4'!AA3+'KPI_VENDEUR 3'!AA3 -> 0 | AB3: =AA3/Z3 -> #DIV/0! | AC3: =+'KPI_VENDEUR 1'!AC3+'KPI_VENDEUR 2'!AC3+'KPI_VENDEUR 5'!AC3+'KPI_VENDEUR 4'!AC3+'KPI_VENDEUR 3'!AC3 -> 0 | AD3: =+'KPI_VENDEUR 1'!AD3+'KPI_VENDEUR 2'!AD3+'KPI_VENDEUR 5'!AD3+'KPI_VENDEUR 4'!AD3+'KPI_VENDEUR 3'!AD3 -> 0 | AE3: =AD3/AC3 -> #DIV/0! | AF3: =+'KPI_VENDEUR 1'!AF3+'KPI_VENDEUR 2'!AF3+'KPI_VENDEUR 5'!AF3+'KPI_VENDEUR 4'!AF3+'KPI_VENDEUR 3'!AF3 -> 0 | AG3: =+'KPI_VENDEUR 1'!AG3+'KPI_VENDEUR 2'!AG3+'KPI_VENDEUR 5'!AG3+'KPI_VENDEUR 4'!AG3+'KPI_VENDEUR 3'!AG3 -> 0 | AH3: =AG3/AF3 -> #DIV/0! | AI3: =+'KPI_VENDEUR 1'!AI3+'KPI_VENDEUR 2'!AI3+'KPI_VENDEUR 5'!AI3+'KPI_VENDEUR 4'!AI3+'KPI_VENDEUR 3'!AI3 -> 0 | AJ3: =+'KPI_VENDEUR 1'!AJ3+'KPI_VENDEUR 2'!AJ3+'KPI_VENDEUR 5'!AJ3+'KPI_VENDEUR 4'!AJ3+'KPI_VENDEUR 3'!AJ3 -> 0 | AK3: =AJ3/AI3 -> #DIV/0! | AL3: =+'KPI_VENDEUR 1'!AL3+'KPI_VENDEUR 2'!AL3+'KPI_VENDEUR 5'!AL3+'KPI_VENDEUR 4'!AL3+'KPI_VENDEUR 3'!AL3 -> 0 | AM3: =+'KPI_VENDEUR 1'!AM3+'KPI_VENDEUR 2'!AM3+'KPI_VENDEUR 5'!AM3+'KPI_VENDEUR 4'!AM3+'KPI_VENDEUR 3'!AM3 -> 0 | AN3: =AM3/AL3 -> #DIV/0!
A4: Nombre d'offres commerciales | B4: =+'KPI_VENDEUR 1'!B4+'KPI_VENDEUR 2'!B4+'KPI_VENDEUR 5'!B4+'KPI_VENDEUR 4'!B4+'KPI_VENDEUR 3'!B4 -> 0 | C4: =+'KPI_VENDEUR 1'!C4+'KPI_VENDEUR 2'!C4+'KPI_VENDEUR 5'!C4+'KPI_VENDEUR 4'!C4+'KPI_VENDEUR 3'!C4 -> 0 | D4: =C4/B4 -> #DIV/0! | E4: =+'KPI_VENDEUR 1'!E4+'KPI_VENDEUR 2'!E4+'KPI_VENDEUR 5'!E4+'KPI_VENDEUR 4'!E4+'KPI_VENDEUR 3'!E4 -> 0 | F4: =+'KPI_VENDEUR 1'!F4+'KPI_VENDEUR 2'!F4+'KPI_VENDEUR 5'!F4+'KPI_VENDEUR 4'!F4+'KPI_VENDEUR 3'!F4 -> 0 | G4: =F4/E4 -> #DIV/0! | H4: =+'KPI_VENDEUR 1'!H4+'KPI_VENDEUR 2'!H4+'KPI_VENDEUR 5'!H4+'KPI_VENDEUR 4'!H4+'KPI_VENDEUR 3'!H4 -> 0 | I4: =+'KPI_VENDEUR 1'!I4+'KPI_VENDEUR 2'!I4+'KPI_VENDEUR 5'!I4+'KPI_VENDEUR 4'!I4+'KPI_VENDEUR 3'!I4 -> 0 | J4: =I4/H4 -> #DIV/0! | K4: =+'KPI_VENDEUR 1'!K4+'KPI_VENDEUR 2'!K4+'KPI_VENDEUR 5'!K4+'KPI_VENDEUR 4'!K4+'KPI_VENDEUR 3'!K4 -> 0 | L4: =+'KPI_VENDEUR 1'!L4+'KPI_VENDEUR 2'!L4+'KPI_VENDEUR 5'!L4+'KPI_VENDEUR 4'!L4+'KPI_VENDEUR 3'!L4 -> 0 | M4: =L4/K4 -> #DIV/0! | N4: =+'KPI_VENDEUR 1'!N4+'KPI_VENDEUR 2'!N4+'KPI_VENDEUR 5'!N4+'KPI_VENDEUR 4'!N4+'KPI_VENDEUR 3'!N4 -> 0 | O4: =+'KPI_VENDEUR 1'!O4+'KPI_VENDEUR 2'!O4+'KPI_VENDEUR 5'!O4+'KPI_VENDEUR 4'!O4+'KPI_VENDEUR 3'!O4 -> 0 | P4: =O4/N4 -> #DIV/0! | Q4: =+'KPI_VENDEUR 1'!Q4+'KPI_VENDEUR 2'!Q4+'KPI_VENDEUR 5'!Q4+'KPI_VENDEUR 4'!Q4+'KPI_VENDEUR 3'!Q4 -> 0 | R4: =+'KPI_VENDEUR 1'!R4+'KPI_VENDEUR 2'!R4+'KPI_VENDEUR 5'!R4+'KPI_VENDEUR 4'!R4+'KPI_VENDEUR 3'!R4 -> 0 | S4: =R4/Q4 -> #DIV/0! | T4: =+'KPI_VENDEUR 1'!T4+'KPI_VENDEUR 2'!T4+'KPI_VENDEUR 5'!T4+'KPI_VENDEUR 4'!T4+'KPI_VENDEUR 3'!T4 -> 0 | U4: =+'KPI_VENDEUR 1'!U4+'KPI_VENDEUR 2'!U4+'KPI_VENDEUR 5'!U4+'KPI_VENDEUR 4'!U4+'KPI_VENDEUR 3'!U4 -> 0 | V4: =U4/T4 -> #DIV/0! | W4: =+'KPI_VENDEUR 1'!W4+'KPI_VENDEUR 2'!W4+'KPI_VENDEUR 5'!W4+'KPI_VENDEUR 4'!W4+'KPI_VENDEUR 3'!W4 -> 0 | X4: =+'KPI_VENDEUR 1'!X4+'KPI_VENDEUR 2'!X4+'KPI_VENDEUR 5'!X4+'KPI_VENDEUR 4'!X4+'KPI_VENDEUR 3'!X4 -> 0 | Y4: =X4/W4 -> #DIV/0! | Z4: =+'KPI_VENDEUR 1'!Z4+'KPI_VENDEUR 2'!Z4+'KPI_VENDEUR 5'!Z4+'KPI_VENDEUR 4'!Z4+'KPI_VENDEUR 3'!Z4 -> 0 | AA4: =+'KPI_VENDEUR 1'!AA4+'KPI_VENDEUR 2'!AA4+'KPI_VENDEUR 5'!AA4+'KPI_VENDEUR 4'!AA4+'KPI_VENDEUR 3'!AA4 -> 0 | AB4: =AA4/Z4 -> #DIV/0! | AC4: =+'KPI_VENDEUR 1'!AC4+'KPI_VENDEUR 2'!AC4+'KPI_VENDEUR 5'!AC4+'KPI_VENDEUR 4'!AC4+'KPI_VENDEUR 3'!AC4 -> 0 | AD4: =+'KPI_VENDEUR 1'!AD4+'KPI_VENDEUR 2'!AD4+'KPI_VENDEUR 5'!AD4+'KPI_VENDEUR 4'!AD4+'KPI_VENDEUR 3'!AD4 -> 0 | AE4: =AD4/AC4 -> #DIV/0! | AF4: =+'KPI_VENDEUR 1'!AF4+'KPI_VENDEUR 2'!AF4+'KPI_VENDEUR 5'!AF4+'KPI_VENDEUR 4'!AF4+'KPI_VENDEUR 3'!AF4 -> 0 | AG4: =+'KPI_VENDEUR 1'!AG4+'KPI_VENDEUR 2'!AG4+'KPI_VENDEUR 5'!AG4+'KPI_VENDEUR 4'!AG4+'KPI_VENDEUR 3'!AG4 -> 0 | AH4: =AG4/AF4 -> #DIV/0! | AI4: =+'KPI_VENDEUR 1'!AI4+'KPI_VENDEUR 2'!AI4+'KPI_VENDEUR 5'!AI4+'KPI_VENDEUR 4'!AI4+'KPI_VENDEUR 3'!AI4 -> 0 | AJ4: =+'KPI_VENDEUR 1'!AJ4+'KPI_VENDEUR 2'!AJ4+'KPI_VENDEUR 5'!AJ4+'KPI_VENDEUR 4'!AJ4+'KPI_VENDEUR 3'!AJ4 -> 0 | AK4: =AJ4/AI4 -> #DIV/0! | AL4: =+'KPI_VENDEUR 1'!AL4+'KPI_VENDEUR 2'!AL4+'KPI_VENDEUR 5'!AL4+'KPI_VENDEUR 4'!AL4+'KPI_VENDEUR 3'!AL4 -> 0 | AM4: =+'KPI_VENDEUR 1'!AM4+'KPI_VENDEUR 2'!AM4+'KPI_VENDEUR 5'!AM4+'KPI_VENDEUR 4'!AM4+'KPI_VENDEUR 3'!AM4 -> 0 | AN4: =AM4/AL4 -> #DIV/0!
A5: Taux de clôture | B5: =+'KPI_VENDEUR 1'!B5+'KPI_VENDEUR 2'!B5+'KPI_VENDEUR 5'!B5+'KPI_VENDEUR 4'!B5+'KPI_VENDEUR 3'!B5 -> 0 | C5: =+'KPI_VENDEUR 1'!C5+'KPI_VENDEUR 2'!C5+'KPI_VENDEUR 5'!C5+'KPI_VENDEUR 4'!C5+'KPI_VENDEUR 3'!C5 -> 0 | D5: =C5/C4 -> #DIV/0! | E5: =+'KPI_VENDEUR 1'!E5+'KPI_VENDEUR 2'!E5+'KPI_VENDEUR 5'!E5+'KPI_VENDEUR 4'!E5+'KPI_VENDEUR 3'!E5 -> 0 | F5: =+'KPI_VENDEUR 1'!F5+'KPI_VENDEUR 2'!F5+'KPI_VENDEUR 5'!F5+'KPI_VENDEUR 4'!F5+'KPI_VENDEUR 3'!F5 -> 0 | G5: =F5/F4 -> #DIV/0! | H5: =+'KPI_VENDEUR 1'!H5+'KPI_VENDEUR 2'!H5+'KPI_VENDEUR 5'!H5+'KPI_VENDEUR 4'!H5+'KPI_VENDEUR 3'!H5 -> 0 | I5: =+'KPI_VENDEUR 1'!I5+'KPI_VENDEUR 2'!I5+'KPI_VENDEUR 5'!I5+'KPI_VENDEUR 4'!I5+'KPI_VENDEUR 3'!I5 -> 0 | J5: =I5/I4 -> #DIV/0! | K5: =+'KPI_VENDEUR 1'!K5+'KPI_VENDEUR 2'!K5+'KPI_VENDEUR 5'!K5+'KPI_VENDEUR 4'!K5+'KPI_VENDEUR 3'!K5 -> 0 | L5: =+'KPI_VENDEUR 1'!L5+'KPI_VENDEUR 2'!L5+'KPI_VENDEUR 5'!L5+'KPI_VENDEUR 4'!L5+'KPI_VENDEUR 3'!L5 -> 0 | M5: =L5/L4 -> #DIV/0! | N5: =+'KPI_VENDEUR 1'!N5+'KPI_VENDEUR 2'!N5+'KPI_VENDEUR 5'!N5+'KPI_VENDEUR 4'!N5+'KPI_VENDEUR 3'!N5 -> 0 | O5: =+'KPI_VENDEUR 1'!O5+'KPI_VENDEUR 2'!O5+'KPI_VENDEUR 5'!O5+'KPI_VENDEUR 4'!O5+'KPI_VENDEUR 3'!O5 -> 0 | P5: =O5/O4 -> #DIV/0! | Q5: =+'KPI_VENDEUR 1'!Q5+'KPI_VENDEUR 2'!Q5+'KPI_VENDEUR 5'!Q5+'KPI_VENDEUR 4'!Q5+'KPI_VENDEUR 3'!Q5 -> 0 | R5: =+'KPI_VENDEUR 1'!R5+'KPI_VENDEUR 2'!R5+'KPI_VENDEUR 5'!R5+'KPI_VENDEUR 4'!R5+'KPI_VENDEUR 3'!R5 -> 0 | S5: =R5/R4 -> #DIV/0! | T5: =+'KPI_VENDEUR 1'!T5+'KPI_VENDEUR 2'!T5+'KPI_VENDEUR 5'!T5+'KPI_VENDEUR 4'!T5+'KPI_VENDEUR 3'!T5 -> 0 | U5: =+'KPI_VENDEUR 1'!U5+'KPI_VENDEUR 2'!U5+'KPI_VENDEUR 5'!U5+'KPI_VENDEUR 4'!U5+'KPI_VENDEUR 3'!U5 -> 0 | V5: =U5/U4 -> #DIV/0! | W5: =+'KPI_VENDEUR 1'!W5+'KPI_VENDEUR 2'!W5+'KPI_VENDEUR 5'!W5+'KPI_VENDEUR 4'!W5+'KPI_VENDEUR 3'!W5 -> 0 | X5: =+'KPI_VENDEUR 1'!X5+'KPI_VENDEUR 2'!X5+'KPI_VENDEUR 5'!X5+'KPI_VENDEUR 4'!X5+'KPI_VENDEUR 3'!X5 -> 0 | Y5: =X5/X4 -> #DIV/0! | Z5: =+'KPI_VENDEUR 1'!Z5+'KPI_VENDEUR 2'!Z5+'KPI_VENDEUR 5'!Z5+'KPI_VENDEUR 4'!Z5+'KPI_VENDEUR 3'!Z5 -> 0 | AA5: =+'KPI_VENDEUR 1'!AA5+'KPI_VENDEUR 2'!AA5+'KPI_VENDEUR 5'!AA5+'KPI_VENDEUR 4'!AA5+'KPI_VENDEUR 3'!AA5 -> 0 | AB5: =AA5/AA4 -> #DIV/0! | AC5: =+'KPI_VENDEUR 1'!AC5+'KPI_VENDEUR 2'!AC5+'KPI_VENDEUR 5'!AC5+'KPI_VENDEUR 4'!AC5+'KPI_VENDEUR 3'!AC5 -> 0 | AD5: =+'KPI_VENDEUR 1'!AD5+'KPI_VENDEUR 2'!AD5+'KPI_VENDEUR 5'!AD5+'KPI_VENDEUR 4'!AD5+'KPI_VENDEUR 3'!AD5 -> 0 | AE5: =AD5/AD4 -> #DIV/0! | AF5: =+'KPI_VENDEUR 1'!AF5+'KPI_VENDEUR 2'!AF5+'KPI_VENDEUR 5'!AF5+'KPI_VENDEUR 4'!AF5+'KPI_VENDEUR 3'!AF5 -> 0 | AG5: =+'KPI_VENDEUR 1'!AG5+'KPI_VENDEUR 2'!AG5+'KPI_VENDEUR 5'!AG5+'KPI_VENDEUR 4'!AG5+'KPI_VENDEUR 3'!AG5 -> 0 | AH5: =AG5/AG4 -> #DIV/0! | AI5: =+'KPI_VENDEUR 1'!AI5+'KPI_VENDEUR 2'!AI5+'KPI_VENDEUR 5'!AI5+'KPI_VENDEUR 4'!AI5+'KPI_VENDEUR 3'!AI5 -> 0 | AJ5: =+'KPI_VENDEUR 1'!AJ5+'KPI_VENDEUR 2'!AJ5+'KPI_VENDEUR 5'!AJ5+'KPI_VENDEUR 4'!AJ5+'KPI_VENDEUR 3'!AJ5 -> 0 | AK5: =AJ5/AJ4 -> #DIV/0! | AL5: =+'KPI_VENDEUR 1'!AL5+'KPI_VENDEUR 2'!AL5+'KPI_VENDEUR 5'!AL5+'KPI_VENDEUR 4'!AL5+'KPI_VENDEUR 3'!AL5 -> 0 | AM5: =+'KPI_VENDEUR 1'!AM5+'KPI_VENDEUR 2'!AM5+'KPI_VENDEUR 5'!AM5+'KPI_VENDEUR 4'!AM5+'KPI_VENDEUR 3'!AM5 -> 0 | AN5: =AM5/AM4 -> #DIV/0!
A6: QTE MANITOU | B6: =+'KPI_VENDEUR 1'!B6+'KPI_VENDEUR 2'!B6+'KPI_VENDEUR 5'!B6+'KPI_VENDEUR 4'!B6+'KPI_VENDEUR 3'!B6 -> 0 | C6: =+'KPI_VENDEUR 1'!C6+'KPI_VENDEUR 2'!C6+'KPI_VENDEUR 5'!C6+'KPI_VENDEUR 4'!C6+'KPI_VENDEUR 3'!C6 -> 0 | D6: =C6/C5 -> #DIV/0! | E6: =+'KPI_VENDEUR 1'!E6+'KPI_VENDEUR 2'!E6+'KPI_VENDEUR 5'!E6+'KPI_VENDEUR 4'!E6+'KPI_VENDEUR 3'!E6 -> 0 | F6: =+'KPI_VENDEUR 1'!F6+'KPI_VENDEUR 2'!F6+'KPI_VENDEUR 5'!F6+'KPI_VENDEUR 4'!F6+'KPI_VENDEUR 3'!F6 -> 0 | G6: =F6/F5 -> #DIV/0! | H6: =+'KPI_VENDEUR 1'!H6+'KPI_VENDEUR 2'!H6+'KPI_VENDEUR 5'!H6+'KPI_VENDEUR 4'!H6+'KPI_VENDEUR 3'!H6 -> 0 | I6: =+'KPI_VENDEUR 1'!I6+'KPI_VENDEUR 2'!I6+'KPI_VENDEUR 5'!I6+'KPI_VENDEUR 4'!I6+'KPI_VENDEUR 3'!I6 -> 0 | J6: =I6/I5 -> #DIV/0! | K6: =+'KPI_VENDEUR 1'!K6+'KPI_VENDEUR 2'!K6+'KPI_VENDEUR 5'!K6+'KPI_VENDEUR 4'!K6+'KPI_VENDEUR 3'!K6 -> 0 | L6: =+'KPI_VENDEUR 1'!L6+'KPI_VENDEUR 2'!L6+'KPI_VENDEUR 5'!L6+'KPI_VENDEUR 4'!L6+'KPI_VENDEUR 3'!L6 -> 0 | M6: =L6/L5 -> #DIV/0! | N6: =+'KPI_VENDEUR 1'!N6+'KPI_VENDEUR 2'!N6+'KPI_VENDEUR 5'!N6+'KPI_VENDEUR 4'!N6+'KPI_VENDEUR 3'!N6 -> 0 | O6: =+'KPI_VENDEUR 1'!O6+'KPI_VENDEUR 2'!O6+'KPI_VENDEUR 5'!O6+'KPI_VENDEUR 4'!O6+'KPI_VENDEUR 3'!O6 -> 0 | P6: =O6/O5 -> #DIV/0! | Q6: =+'KPI_VENDEUR 1'!Q6+'KPI_VENDEUR 2'!Q6+'KPI_VENDEUR 5'!Q6+'KPI_VENDEUR 4'!Q6+'KPI_VENDEUR 3'!Q6 -> 0 | R6: =+'KPI_VENDEUR 1'!R6+'KPI_VENDEUR 2'!R6+'KPI_VENDEUR 5'!R6+'KPI_VENDEUR 4'!R6+'KPI_VENDEUR 3'!R6 -> 0 | S6: =R6/R5 -> #DIV/0! | T6: =+'KPI_VENDEUR 1'!T6+'KPI_VENDEUR 2'!T6+'KPI_VENDEUR 5'!T6+'KPI_VENDEUR 4'!T6+'KPI_VENDEUR 3'!T6 -> 0 | U6: =+'KPI_VENDEUR 1'!U6+'KPI_VENDEUR 2'!U6+'KPI_VENDEUR 5'!U6+'KPI_VENDEUR 4'!U6+'KPI_VENDEUR 3'!U6 -> 0 | V6: =U6/U5 -> #DIV/0! | W6: =+'KPI_VENDEUR 1'!W6+'KPI_VENDEUR 2'!W6+'KPI_VENDEUR 5'!W6+'KPI_VENDEUR 4'!W6+'KPI_VENDEUR 3'!W6 -> 0 | X6: =+'KPI_VENDEUR 1'!X6+'KPI_VENDEUR 2'!X6+'KPI_VENDEUR 5'!X6+'KPI_VENDEUR 4'!X6+'KPI_VENDEUR 3'!X6 -> 0 | Y6: =X6/X5 -> #DIV/0! | Z6: =+'KPI_VENDEUR 1'!Z6+'KPI_VENDEUR 2'!Z6+'KPI_VENDEUR 5'!Z6+'KPI_VENDEUR 4'!Z6+'KPI_VENDEUR 3'!Z6 -> 0 | AA6: =+'KPI_VENDEUR 1'!AA6+'KPI_VENDEUR 2'!AA6+'KPI_VENDEUR 5'!AA6+'KPI_VENDEUR 4'!AA6+'KPI_VENDEUR 3'!AA6 -> 0 | AB6: =AA6/AA5 -> #DIV/0! | AC6: =+'KPI_VENDEUR 1'!AC6+'KPI_VENDEUR 2'!AC6+'KPI_VENDEUR 5'!AC6+'KPI_VENDEUR 4'!AC6+'KPI_VENDEUR 3'!AC6 -> 0 | AD6: =+'KPI_VENDEUR 1'!AD6+'KPI_VENDEUR 2'!AD6+'KPI_VENDEUR 5'!AD6+'KPI_VENDEUR 4'!AD6+'KPI_VENDEUR 3'!AD6 -> 0 | AE6: =AD6/AD5 -> #DIV/0! | AF6: =+'KPI_VENDEUR 1'!AF6+'KPI_VENDEUR 2'!AF6+'KPI_VENDEUR 5'!AF6+'KPI_VENDEUR 4'!AF6+'KPI_VENDEUR 3'!AF6 -> 0 | AG6: =+'KPI_VENDEUR 1'!AG6+'KPI_VENDEUR 2'!AG6+'KPI_VENDEUR 5'!AG6+'KPI_VENDEUR 4'!AG6+'KPI_VENDEUR 3'!AG6 -> 0 | AH6: =AG6/AG5 -> #DIV/0! | AI6: =+'KPI_VENDEUR 1'!AI6+'KPI_VENDEUR 2'!AI6+'KPI_VENDEUR 5'!AI6+'KPI_VENDEUR 4'!AI6+'KPI_VENDEUR 3'!AI6 -> 0 | AJ6: =+'KPI_VENDEUR 1'!AJ6+'KPI_VENDEUR 2'!AJ6+'KPI_VENDEUR 5'!AJ6+'KPI_VENDEUR 4'!AJ6+'KPI_VENDEUR 3'!AJ6 -> 0 | AK6: =AJ6/AJ5 -> #DIV/0! | AL6: =+'KPI_VENDEUR 1'!AL6+'KPI_VENDEUR 2'!AL6+'KPI_VENDEUR 5'!AL6+'KPI_VENDEUR 4'!AL6+'KPI_VENDEUR 3'!AL6 -> 0 | AM6: =+'KPI_VENDEUR 1'!AM6+'KPI_VENDEUR 2'!AM6+'KPI_VENDEUR 5'!AM6+'KPI_VENDEUR 4'!AM6+'KPI_VENDEUR 3'!AM6 -> 0 | AN6: =AM6/AM5 -> #DIV/0!
A7: QTE KALMAR | B7: =+'KPI_VENDEUR 1'!B7+'KPI_VENDEUR 2'!B7+'KPI_VENDEUR 5'!B7+'KPI_VENDEUR 4'!B7+'KPI_VENDEUR 3'!B7 -> 0 | C7: =+'KPI_VENDEUR 1'!C7+'KPI_VENDEUR 2'!C7+'KPI_VENDEUR 5'!C7+'KPI_VENDEUR 4'!C7+'KPI_VENDEUR 3'!C7 -> 0 | D7: =C7/C6 -> #DIV/0! | E7: =+'KPI_VENDEUR 1'!E7+'KPI_VENDEUR 2'!E7+'KPI_VENDEUR 5'!E7+'KPI_VENDEUR 4'!E7+'KPI_VENDEUR 3'!E7 -> 0 | F7: =+'KPI_VENDEUR 1'!F7+'KPI_VENDEUR 2'!F7+'KPI_VENDEUR 5'!F7+'KPI_VENDEUR 4'!F7+'KPI_VENDEUR 3'!F7 -> 0 | G7: =F7/F6 -> #DIV/0! | H7: =+'KPI_VENDEUR 1'!H7+'KPI_VENDEUR 2'!H7+'KPI_VENDEUR 5'!H7+'KPI_VENDEUR 4'!H7+'KPI_VENDEUR 3'!H7 -> 0 | I7: =+'KPI_VENDEUR 1'!I7+'KPI_VENDEUR 2'!I7+'KPI_VENDEUR 5'!I7+'KPI_VENDEUR 4'!I7+'KPI_VENDEUR 3'!I7 -> 0 | J7: =I7/I6 -> #DIV/0! | K7: =+'KPI_VENDEUR 1'!K7+'KPI_VENDEUR 2'!K7+'KPI_VENDEUR 5'!K7+'KPI_VENDEUR 4'!K7+'KPI_VENDEUR 3'!K7 -> 0 | L7: =+'KPI_VENDEUR 1'!L7+'KPI_VENDEUR 2'!L7+'KPI_VENDEUR 5'!L7+'KPI_VENDEUR 4'!L7+'KPI_VENDEUR 3'!L7 -> 0 | M7: =L7/L6 -> #DIV/0! | N7: =+'KPI_VENDEUR 1'!N7+'KPI_VENDEUR 2'!N7+'KPI_VENDEUR 5'!N7+'KPI_VENDEUR 4'!N7+'KPI_VENDEUR 3'!N7 -> 0 | O7: =+'KPI_VENDEUR 1'!O7+'KPI_VENDEUR 2'!O7+'KPI_VENDEUR 5'!O7+'KPI_VENDEUR 4'!O7+'KPI_VENDEUR 3'!O7 -> 0 | P7: =O7/O6 -> #DIV/0! | Q7: =+'KPI_VENDEUR 1'!Q7+'KPI_VENDEUR 2'!Q7+'KPI_VENDEUR 5'!Q7+'KPI_VENDEUR 4'!Q7+'KPI_VENDEUR 3'!Q7 -> 0 | R7: =+'KPI_VENDEUR 1'!R7+'KPI_VENDEUR 2'!R7+'KPI_VENDEUR 5'!R7+'KPI_VENDEUR 4'!R7+'KPI_VENDEUR 3'!R7 -> 0 | S7: =R7/R6 -> #DIV/0! | T7: =+'KPI_VENDEUR 1'!T7+'KPI_VENDEUR 2'!T7+'KPI_VENDEUR 5'!T7+'KPI_VENDEUR 4'!T7+'KPI_VENDEUR 3'!T7 -> 0 | U7: =+'KPI_VENDEUR 1'!U7+'KPI_VENDEUR 2'!U7+'KPI_VENDEUR 5'!U7+'KPI_VENDEUR 4'!U7+'KPI_VENDEUR 3'!U7 -> 0 | V7: =U7/U6 -> #DIV/0! | W7: =+'KPI_VENDEUR 1'!W7+'KPI_VENDEUR 2'!W7+'KPI_VENDEUR 5'!W7+'KPI_VENDEUR 4'!W7+'KPI_VENDEUR 3'!W7 -> 0 | X7: =+'KPI_VENDEUR 1'!X7+'KPI_VENDEUR 2'!X7+'KPI_VENDEUR 5'!X7+'KPI_VENDEUR 4'!X7+'KPI_VENDEUR 3'!X7 -> 0 | Y7: =X7/X6 -> #DIV/0! | Z7: =+'KPI_VENDEUR 1'!Z7+'KPI_VENDEUR 2'!Z7+'KPI_VENDEUR 5'!Z7+'KPI_VENDEUR 4'!Z7+'KPI_VENDEUR 3'!Z7 -> 0 | AA7: =+'KPI_VENDEUR 1'!AA7+'KPI_VENDEUR 2'!AA7+'KPI_VENDEUR 5'!AA7+'KPI_VENDEUR 4'!AA7+'KPI_VENDEUR 3'!AA7 -> 0 | AB7: =AA7/AA6 -> #DIV/0! | AC7: =+'KPI_VENDEUR 1'!AC7+'KPI_VENDEUR 2'!AC7+'KPI_VENDEUR 5'!AC7+'KPI_VENDEUR 4'!AC7+'KPI_VENDEUR 3'!AC7 -> 0 | AD7: =+'KPI_VENDEUR 1'!AD7+'KPI_VENDEUR 2'!AD7+'KPI_VENDEUR 5'!AD7+'KPI_VENDEUR 4'!AD7+'KPI_VENDEUR 3'!AD7 -> 0 | AE7: =AD7/AD6 -> #DIV/0! | AF7: =+'KPI_VENDEUR 1'!AF7+'KPI_VENDEUR 2'!AF7+'KPI_VENDEUR 5'!AF7+'KPI_VENDEUR 4'!AF7+'KPI_VENDEUR 3'!AF7 -> 0 | AG7: =+'KPI_VENDEUR 1'!AG7+'KPI_VENDEUR 2'!AG7+'KPI_VENDEUR 5'!AG7+'KPI_VENDEUR 4'!AG7+'KPI_VENDEUR 3'!AG7 -> 0 | AH7: =AG7/AG6 -> #DIV/0! | AI7: =+'KPI_VENDEUR 1'!AI7+'KPI_VENDEUR 2'!AI7+'KPI_VENDEUR 5'!AI7+'KPI_VENDEUR 4'!AI7+'KPI_VENDEUR 3'!AI7 -> 0 | AJ7: =+'KPI_VENDEUR 1'!AJ7+'KPI_VENDEUR 2'!AJ7+'KPI_VENDEUR 5'!AJ7+'KPI_VENDEUR 4'!AJ7+'KPI_VENDEUR 3'!AJ7 -> 0 | AK7: =AJ7/AJ6 -> #DIV/0! | AL7: =+'KPI_VENDEUR 1'!AL7+'KPI_VENDEUR 2'!AL7+'KPI_VENDEUR 5'!AL7+'KPI_VENDEUR 4'!AL7+'KPI_VENDEUR 3'!AL7 -> 0 | AM7: =+'KPI_VENDEUR 1'!AM7+'KPI_VENDEUR 2'!AM7+'KPI_VENDEUR 5'!AM7+'KPI_VENDEUR 4'!AM7+'KPI_VENDEUR 3'!AM7 -> 0 | AN7: =AM7/AM6 -> #DIV/0!
A8: QTE MASSEY FERGUSON | B8: =+'KPI_VENDEUR 1'!B8+'KPI_VENDEUR 2'!B8+'KPI_VENDEUR 5'!B8+'KPI_VENDEUR 4'!B8+'KPI_VENDEUR 3'!B8 -> 0 | C8: =+'KPI_VENDEUR 1'!C8+'KPI_VENDEUR 2'!C8+'KPI_VENDEUR 5'!C8+'KPI_VENDEUR 4'!C8+'KPI_VENDEUR 3'!C8 -> 0 | D8: =C8/C7 -> #DIV/0! | E8: =+'KPI_VENDEUR 1'!E8+'KPI_VENDEUR 2'!E8+'KPI_VENDEUR 5'!E8+'KPI_VENDEUR 4'!E8+'KPI_VENDEUR 3'!E8 -> 0 | F8: =+'KPI_VENDEUR 1'!F8+'KPI_VENDEUR 2'!F8+'KPI_VENDEUR 5'!F8+'KPI_VENDEUR 4'!F8+'KPI_VENDEUR 3'!F8 -> 0 | G8: =F8/F7 -> #DIV/0! | H8: =+'KPI_VENDEUR 1'!H8+'KPI_VENDEUR 2'!H8+'KPI_VENDEUR 5'!H8+'KPI_VENDEUR 4'!H8+'KPI_VENDEUR 3'!H8 -> 0 | I8: =+'KPI_VENDEUR 1'!I8+'KPI_VENDEUR 2'!I8+'KPI_VENDEUR 5'!I8+'KPI_VENDEUR 4'!I8+'KPI_VENDEUR 3'!I8 -> 0 | J8: =I8/I7 -> #DIV/0! | K8: =+'KPI_VENDEUR 1'!K8+'KPI_VENDEUR 2'!K8+'KPI_VENDEUR 5'!K8+'KPI_VENDEUR 4'!K8+'KPI_VENDEUR 3'!K8 -> 0 | L8: =+'KPI_VENDEUR 1'!L8+'KPI_VENDEUR 2'!L8+'KPI_VENDEUR 5'!L8+'KPI_VENDEUR 4'!L8+'KPI_VENDEUR 3'!L8 -> 0 | M8: =L8/L7 -> #DIV/0! | N8: =+'KPI_VENDEUR 1'!N8+'KPI_VENDEUR 2'!N8+'KPI_VENDEUR 5'!N8+'KPI_VENDEUR 4'!N8+'KPI_VENDEUR 3'!N8 -> 0 | O8: =+'KPI_VENDEUR 1'!O8+'KPI_VENDEUR 2'!O8+'KPI_VENDEUR 5'!O8+'KPI_VENDEUR 4'!O8+'KPI_VENDEUR 3'!O8 -> 0 | P8: =O8/O7 -> #DIV/0! | Q8: =+'KPI_VENDEUR 1'!Q8+'KPI_VENDEUR 2'!Q8+'KPI_VENDEUR 5'!Q8+'KPI_VENDEUR 4'!Q8+'KPI_VENDEUR 3'!Q8 -> 0 | R8: =+'KPI_VENDEUR 1'!R8+'KPI_VENDEUR 2'!R8+'KPI_VENDEUR 5'!R8+'KPI_VENDEUR 4'!R8+'KPI_VENDEUR 3'!R8 -> 0 | S8: =R8/R7 -> #DIV/0! | T8: =+'KPI_VENDEUR 1'!T8+'KPI_VENDEUR 2'!T8+'KPI_VENDEUR 5'!T8+'KPI_VENDEUR 4'!T8+'KPI_VENDEUR 3'!T8 -> 0 | U8: =+'KPI_VENDEUR 1'!U8+'KPI_VENDEUR 2'!U8+'KPI_VENDEUR 5'!U8+'KPI_VENDEUR 4'!U8+'KPI_VENDEUR 3'!U8 -> 0 | V8: =U8/U7 -> #DIV/0! | W8: =+'KPI_VENDEUR 1'!W8+'KPI_VENDEUR 2'!W8+'KPI_VENDEUR 5'!W8+'KPI_VENDEUR 4'!W8+'KPI_VENDEUR 3'!W8 -> 0 | X8: =+'KPI_VENDEUR 1'!X8+'KPI_VENDEUR 2'!X8+'KPI_VENDEUR 5'!X8+'KPI_VENDEUR 4'!X8+'KPI_VENDEUR 3'!X8 -> 0 | Y8: =X8/X7 -> #DIV/0! | Z8: =+'KPI_VENDEUR 1'!Z8+'KPI_VENDEUR 2'!Z8+'KPI_VENDEUR 5'!Z8+'KPI_VENDEUR 4'!Z8+'KPI_VENDEUR 3'!Z8 -> 0 | AA8: =+'KPI_VENDEUR 1'!AA8+'KPI_VENDEUR 2'!AA8+'KPI_VENDEUR 5'!AA8+'KPI_VENDEUR 4'!AA8+'KPI_VENDEUR 3'!AA8 -> 0 | AB8: =AA8/AA7 -> #DIV/0! | AC8: =+'KPI_VENDEUR 1'!AC8+'KPI_VENDEUR 2'!AC8+'KPI_VENDEUR 5'!AC8+'KPI_VENDEUR 4'!AC8+'KPI_VENDEUR 3'!AC8 -> 0 | AD8: =+'KPI_VENDEUR 1'!AD8+'KPI_VENDEUR 2'!AD8+'KPI_VENDEUR 5'!AD8+'KPI_VENDEUR 4'!AD8+'KPI_VENDEUR 3'!AD8 -> 0 | AE8: =AD8/AD7 -> #DIV/0! | AF8: =+'KPI_VENDEUR 1'!AF8+'KPI_VENDEUR 2'!AF8+'KPI_VENDEUR 5'!AF8+'KPI_VENDEUR 4'!AF8+'KPI_VENDEUR 3'!AF8 -> 0 | AG8: =+'KPI_VENDEUR 1'!AG8+'KPI_VENDEUR 2'!AG8+'KPI_VENDEUR 5'!AG8+'KPI_VENDEUR 4'!AG8+'KPI_VENDEUR 3'!AG8 -> 0 | AH8: =AG8/AG7 -> #DIV/0! | AI8: =+'KPI_VENDEUR 1'!AI8+'KPI_VENDEUR 2'!AI8+'KPI_VENDEUR 5'!AI8+'KPI_VENDEUR 4'!AI8+'KPI_VENDEUR 3'!AI8 -> 0 | AJ8: =+'KPI_VENDEUR 1'!AJ8+'KPI_VENDEUR 2'!AJ8+'KPI_VENDEUR 5'!AJ8+'KPI_VENDEUR 4'!AJ8+'KPI_VENDEUR 3'!AJ8 -> 0 | AK8: =AJ8/AJ7 -> #DIV/0! | AL8: =+'KPI_VENDEUR 1'!AL8+'KPI_VENDEUR 2'!AL8+'KPI_VENDEUR 5'!AL8+'KPI_VENDEUR 4'!AL8+'KPI_VENDEUR 3'!AL8 -> 0 | AM8: =+'KPI_VENDEUR 1'!AM8+'KPI_VENDEUR 2'!AM8+'KPI_VENDEUR 5'!AM8+'KPI_VENDEUR 4'!AM8+'KPI_VENDEUR 3'!AM8 -> 0 | AN8: =AM8/AM7 -> #DIV/0!
A9: QTE NARDI | B9: =+'KPI_VENDEUR 1'!B9+'KPI_VENDEUR 2'!B9+'KPI_VENDEUR 5'!B9+'KPI_VENDEUR 4'!B9+'KPI_VENDEUR 3'!B9 -> 0 | C9: =+'KPI_VENDEUR 1'!C9+'KPI_VENDEUR 2'!C9+'KPI_VENDEUR 5'!C9+'KPI_VENDEUR 4'!C9+'KPI_VENDEUR 3'!C9 -> 0 | D9: =C9/C8 -> #DIV/0! | E9: =+'KPI_VENDEUR 1'!E9+'KPI_VENDEUR 2'!E9+'KPI_VENDEUR 5'!E9+'KPI_VENDEUR 4'!E9+'KPI_VENDEUR 3'!E9 -> 0 | F9: =+'KPI_VENDEUR 1'!F9+'KPI_VENDEUR 2'!F9+'KPI_VENDEUR 5'!F9+'KPI_VENDEUR 4'!F9+'KPI_VENDEUR 3'!F9 -> 0 | G9: =F9/F8 -> #DIV/0! | H9: =+'KPI_VENDEUR 1'!H9+'KPI_VENDEUR 2'!H9+'KPI_VENDEUR 5'!H9+'KPI_VENDEUR 4'!H9+'KPI_VENDEUR 3'!H9 -> 0 | I9: =+'KPI_VENDEUR 1'!I9+'KPI_VENDEUR 2'!I9+'KPI_VENDEUR 5'!I9+'KPI_VENDEUR 4'!I9+'KPI_VENDEUR 3'!I9 -> 0 | J9: =I9/I8 -> #DIV/0! | K9: =+'KPI_VENDEUR 1'!K9+'KPI_VENDEUR 2'!K9+'KPI_VENDEUR 5'!K9+'KPI_VENDEUR 4'!K9+'KPI_VENDEUR 3'!K9 -> 0 | L9: =+'KPI_VENDEUR 1'!L9+'KPI_VENDEUR 2'!L9+'KPI_VENDEUR 5'!L9+'KPI_VENDEUR 4'!L9+'KPI_VENDEUR 3'!L9 -> 0 | M9: =L9/L8 -> #DIV/0! | N9: =+'KPI_VENDEUR 1'!N9+'KPI_VENDEUR 2'!N9+'KPI_VENDEUR 5'!N9+'KPI_VENDEUR 4'!N9+'KPI_VENDEUR 3'!N9 -> 0 | O9: =+'KPI_VENDEUR 1'!O9+'KPI_VENDEUR 2'!O9+'KPI_VENDEUR 5'!O9+'KPI_VENDEUR 4'!O9+'KPI_VENDEUR 3'!O9 -> 0 | P9: =O9/O8 -> #DIV/0! | Q9: =+'KPI_VENDEUR 1'!Q9+'KPI_VENDEUR 2'!Q9+'KPI_VENDEUR 5'!Q9+'KPI_VENDEUR 4'!Q9+'KPI_VENDEUR 3'!Q9 -> 0 | R9: =+'KPI_VENDEUR 1'!R9+'KPI_VENDEUR 2'!R9+'KPI_VENDEUR 5'!R9+'KPI_VENDEUR 4'!R9+'KPI_VENDEUR 3'!R9 -> 0 | S9: =R9/R8 -> #DIV/0! | T9: =+'KPI_VENDEUR 1'!T9+'KPI_VENDEUR 2'!T9+'KPI_VENDEUR 5'!T9+'KPI_VENDEUR 4'!T9+'KPI_VENDEUR 3'!T9 -> 0 | U9: =+'KPI_VENDEUR 1'!U9+'KPI_VENDEUR 2'!U9+'KPI_VENDEUR 5'!U9+'KPI_VENDEUR 4'!U9+'KPI_VENDEUR 3'!U9 -> 0 | V9: =U9/U8 -> #DIV/0! | W9: =+'KPI_VENDEUR 1'!W9+'KPI_VENDEUR 2'!W9+'KPI_VENDEUR 5'!W9+'KPI_VENDEUR 4'!W9+'KPI_VENDEUR 3'!W9 -> 0 | X9: =+'KPI_VENDEUR 1'!X9+'KPI_VENDEUR 2'!X9+'KPI_VENDEUR 5'!X9+'KPI_VENDEUR 4'!X9+'KPI_VENDEUR 3'!X9 -> 0 | Y9: =X9/X8 -> #DIV/0! | Z9: =+'KPI_VENDEUR 1'!Z9+'KPI_VENDEUR 2'!Z9+'KPI_VENDEUR 5'!Z9+'KPI_VENDEUR 4'!Z9+'KPI_VENDEUR 3'!Z9 -> 0 | AA9: =+'KPI_VENDEUR 1'!AA9+'KPI_VENDEUR 2'!AA9+'KPI_VENDEUR 5'!AA9+'KPI_VENDEUR 4'!AA9+'KPI_VENDEUR 3'!AA9 -> 0 | AB9: =AA9/AA8 -> #DIV/0! | AC9: =+'KPI_VENDEUR 1'!AC9+'KPI_VENDEUR 2'!AC9+'KPI_VENDEUR 5'!AC9+'KPI_VENDEUR 4'!AC9+'KPI_VENDEUR 3'!AC9 -> 0 | AD9: =+'KPI_VENDEUR 1'!AD9+'KPI_VENDEUR 2'!AD9+'KPI_VENDEUR 5'!AD9+'KPI_VENDEUR 4'!AD9+'KPI_VENDEUR 3'!AD9 -> 0 | AE9: =AD9/AD8 -> #DIV/0! | AF9: =+'KPI_VENDEUR 1'!AF9+'KPI_VENDEUR 2'!AF9+'KPI_VENDEUR 5'!AF9+'KPI_VENDEUR 4'!AF9+'KPI_VENDEUR 3'!AF9 -> 0 | AG9: =+'KPI_VENDEUR 1'!AG9+'KPI_VENDEUR 2'!AG9+'KPI_VENDEUR 5'!AG9+'KPI_VENDEUR 4'!AG9+'KPI_VENDEUR 3'!AG9 -> 0 | AH9: =AG9/AG8 -> #DIV/0! | AI9: =+'KPI_VENDEUR 1'!AI9+'KPI_VENDEUR 2'!AI9+'KPI_VENDEUR 5'!AI9+'KPI_VENDEUR 4'!AI9+'KPI_VENDEUR 3'!AI9 -> 0 | AJ9: =+'KPI_VENDEUR 1'!AJ9+'KPI_VENDEUR 2'!AJ9+'KPI_VENDEUR 5'!AJ9+'KPI_VENDEUR 4'!AJ9+'KPI_VENDEUR 3'!AJ9 -> 0 | AK9: =AJ9/AJ8 -> #DIV/0! | AL9: =+'KPI_VENDEUR 1'!AL9+'KPI_VENDEUR 2'!AL9+'KPI_VENDEUR 5'!AL9+'KPI_VENDEUR 4'!AL9+'KPI_VENDEUR 3'!AL9 -> 0 | AM9: =+'KPI_VENDEUR 1'!AM9+'KPI_VENDEUR 2'!AM9+'KPI_VENDEUR 5'!AM9+'KPI_VENDEUR 4'!AM9+'KPI_VENDEUR 3'!AM9 -> 0 | AN9: =AM9/AM8 -> #DIV/0!
A10: QTE TOTAL VENTES | B10: =+'KPI_VENDEUR 1'!B10+'KPI_VENDEUR 2'!B10+'KPI_VENDEUR 5'!B10+'KPI_VENDEUR 4'!B10+'KPI_VENDEUR 3'!B10 -> 0 | C10: =+'KPI_VENDEUR 1'!C10+'KPI_VENDEUR 2'!C10+'KPI_VENDEUR 5'!C10+'KPI_VENDEUR 4'!C10+'KPI_VENDEUR 3'!C10 -> 0 | D10: =C10/B10 -> #DIV/0! | E10: =+'KPI_VENDEUR 1'!E10+'KPI_VENDEUR 2'!E10+'KPI_VENDEUR 5'!E10+'KPI_VENDEUR 4'!E10+'KPI_VENDEUR 3'!E10 -> 0 | F10: =+'KPI_VENDEUR 1'!F10+'KPI_VENDEUR 2'!F10+'KPI_VENDEUR 5'!F10+'KPI_VENDEUR 4'!F10+'KPI_VENDEUR 3'!F10 -> 0 | G10: =F10/E10 -> #DIV/0! | H10: =+'KPI_VENDEUR 1'!H10+'KPI_VENDEUR 2'!H10+'KPI_VENDEUR 5'!H10+'KPI_VENDEUR 4'!H10+'KPI_VENDEUR 3'!H10 -> 0 | I10: =+'KPI_VENDEUR 1'!I10+'KPI_VENDEUR 2'!I10+'KPI_VENDEUR 5'!I10+'KPI_VENDEUR 4'!I10+'KPI_VENDEUR 3'!I10 -> 0 | J10: =I10/H10 -> #DIV/0! | K10: =+'KPI_VENDEUR 1'!K10+'KPI_VENDEUR 2'!K10+'KPI_VENDEUR 5'!K10+'KPI_VENDEUR 4'!K10+'KPI_VENDEUR 3'!K10 -> 0 | L10: =+'KPI_VENDEUR 1'!L10+'KPI_VENDEUR 2'!L10+'KPI_VENDEUR 5'!L10+'KPI_VENDEUR 4'!L10+'KPI_VENDEUR 3'!L10 -> 0 | M10: =L10/K10 -> #DIV/0! | N10: =+'KPI_VENDEUR 1'!N10+'KPI_VENDEUR 2'!N10+'KPI_VENDEUR 5'!N10+'KPI_VENDEUR 4'!N10+'KPI_VENDEUR 3'!N10 -> 0 | O10: =+'KPI_VENDEUR 1'!O10+'KPI_VENDEUR 2'!O10+'KPI_VENDEUR 5'!O10+'KPI_VENDEUR 4'!O10+'KPI_VENDEUR 3'!O10 -> 0 | P10: =O10/N10 -> #DIV/0! | Q10: =+'KPI_VENDEUR 1'!Q10+'KPI_VENDEUR 2'!Q10+'KPI_VENDEUR 5'!Q10+'KPI_VENDEUR 4'!Q10+'KPI_VENDEUR 3'!Q10 -> 0 | R10: =+'KPI_VENDEUR 1'!R10+'KPI_VENDEUR 2'!R10+'KPI_VENDEUR 5'!R10+'KPI_VENDEUR 4'!R10+'KPI_VENDEUR 3'!R10 -> 0 | S10: =R10/Q10 -> #DIV/0! | T10: =+'KPI_VENDEUR 1'!T10+'KPI_VENDEUR 2'!T10+'KPI_VENDEUR 5'!T10+'KPI_VENDEUR 4'!T10+'KPI_VENDEUR 3'!T10 -> 0 | U10: =+'KPI_VENDEUR 1'!U10+'KPI_VENDEUR 2'!U10+'KPI_VENDEUR 5'!U10+'KPI_VENDEUR 4'!U10+'KPI_VENDEUR 3'!U10 -> 0 | V10: =U10/T10 -> #DIV/0! | W10: =+'KPI_VENDEUR 1'!W10+'KPI_VENDEUR 2'!W10+'KPI_VENDEUR 5'!W10+'KPI_VENDEUR 4'!W10+'KPI_VENDEUR 3'!W10 -> 0 | X10: =+'KPI_VENDEUR 1'!X10+'KPI_VENDEUR 2'!X10+'KPI_VENDEUR 5'!X10+'KPI_VENDEUR 4'!X10+'KPI_VENDEUR 3'!X10 -> 0 | Y10: =X10/W10 -> #DIV/0! | Z10: =+'KPI_VENDEUR 1'!Z10+'KPI_VENDEUR 2'!Z10+'KPI_VENDEUR 5'!Z10+'KPI_VENDEUR 4'!Z10+'KPI_VENDEUR 3'!Z10 -> 0 | AA10: =+'KPI_VENDEUR 1'!AA10+'KPI_VENDEUR 2'!AA10+'KPI_VENDEUR 5'!AA10+'KPI_VENDEUR 4'!AA10+'KPI_VENDEUR 3'!AA10 -> 0 | AB10: =AA10/Z10 -> #DIV/0! | AC10: =+'KPI_VENDEUR 1'!AC10+'KPI_VENDEUR 2'!AC10+'KPI_VENDEUR 5'!AC10+'KPI_VENDEUR 4'!AC10+'KPI_VENDEUR 3'!AC10 -> 0 | AD10: =+'KPI_VENDEUR 1'!AD10+'KPI_VENDEUR 2'!AD10+'KPI_VENDEUR 5'!AD10+'KPI_VENDEUR 4'!AD10+'KPI_VENDEUR 3'!AD10 -> 0 | AE10: =AD10/AC10 -> #DIV/0! | AF10: =+'KPI_VENDEUR 1'!AF10+'KPI_VENDEUR 2'!AF10+'KPI_VENDEUR 5'!AF10+'KPI_VENDEUR 4'!AF10+'KPI_VENDEUR 3'!AF10 -> 0 | AG10: =+'KPI_VENDEUR 1'!AG10+'KPI_VENDEUR 2'!AG10+'KPI_VENDEUR 5'!AG10+'KPI_VENDEUR 4'!AG10+'KPI_VENDEUR 3'!AG10 -> 0 | AH10: =AG10/AF10 -> #DIV/0! | AI10: =+'KPI_VENDEUR 1'!AI10+'KPI_VENDEUR 2'!AI10+'KPI_VENDEUR 5'!AI10+'KPI_VENDEUR 4'!AI10+'KPI_VENDEUR 3'!AI10 -> 0 | AJ10: =+'KPI_VENDEUR 1'!AJ10+'KPI_VENDEUR 2'!AJ10+'KPI_VENDEUR 5'!AJ10+'KPI_VENDEUR 4'!AJ10+'KPI_VENDEUR 3'!AJ10 -> 0 | AK10: =AJ10/AI10 -> #DIV/0! | AL10: =+'KPI_VENDEUR 1'!AL10+'KPI_VENDEUR 2'!AL10+'KPI_VENDEUR 5'!AL10+'KPI_VENDEUR 4'!AL10+'KPI_VENDEUR 3'!AL10 -> 0 | AM10: =+'KPI_VENDEUR 1'!AM10+'KPI_VENDEUR 2'!AM10+'KPI_VENDEUR 5'!AM10+'KPI_VENDEUR 4'!AM10+'KPI_VENDEUR 3'!AM10 -> 0 | AN10: =AM10/AL10 -> #DIV/0!
A11: Chiffre d'Affaires (HT) FCFA | B11: =+'KPI_VENDEUR 1'!B11+'KPI_VENDEUR 2'!B11+'KPI_VENDEUR 5'!B11+'KPI_VENDEUR 4'!B11+'KPI_VENDEUR 3'!B11 -> 0 | C11: =+'KPI_VENDEUR 1'!C11+'KPI_VENDEUR 2'!C11+'KPI_VENDEUR 5'!C11+'KPI_VENDEUR 4'!C11+'KPI_VENDEUR 3'!C11 -> 0 | D11: =C11/B11 -> #DIV/0! | E11: =+'KPI_VENDEUR 1'!E11+'KPI_VENDEUR 2'!E11+'KPI_VENDEUR 5'!E11+'KPI_VENDEUR 4'!E11+'KPI_VENDEUR 3'!E11 -> 0 | F11: =+'KPI_VENDEUR 1'!F11+'KPI_VENDEUR 2'!F11+'KPI_VENDEUR 5'!F11+'KPI_VENDEUR 4'!F11+'KPI_VENDEUR 3'!F11 -> 0 | G11: =F11/E11 -> #DIV/0! | H11: =+'KPI_VENDEUR 1'!H11+'KPI_VENDEUR 2'!H11+'KPI_VENDEUR 5'!H11+'KPI_VENDEUR 4'!H11+'KPI_VENDEUR 3'!H11 -> 0 | I11: =+'KPI_VENDEUR 1'!I11+'KPI_VENDEUR 2'!I11+'KPI_VENDEUR 5'!I11+'KPI_VENDEUR 4'!I11+'KPI_VENDEUR 3'!I11 -> 0 | J11: =I11/H11 -> #DIV/0! | K11: =+'KPI_VENDEUR 1'!K11+'KPI_VENDEUR 2'!K11+'KPI_VENDEUR 5'!K11+'KPI_VENDEUR 4'!K11+'KPI_VENDEUR 3'!K11 -> 0 | L11: =+'KPI_VENDEUR 1'!L11+'KPI_VENDEUR 2'!L11+'KPI_VENDEUR 5'!L11+'KPI_VENDEUR 4'!L11+'KPI_VENDEUR 3'!L11 -> 0 | M11: =L11/K11 -> #DIV/0! | N11: =+'KPI_VENDEUR 1'!N11+'KPI_VENDEUR 2'!N11+'KPI_VENDEUR 5'!N11+'KPI_VENDEUR 4'!N11+'KPI_VENDEUR 3'!N11 -> 0 | O11: =+'KPI_VENDEUR 1'!O11+'KPI_VENDEUR 2'!O11+'KPI_VENDEUR 5'!O11+'KPI_VENDEUR 4'!O11+'KPI_VENDEUR 3'!O11 -> 0 | P11: =O11/N11 -> #DIV/0! | Q11: =+'KPI_VENDEUR 1'!Q11+'KPI_VENDEUR 2'!Q11+'KPI_VENDEUR 5'!Q11+'KPI_VENDEUR 4'!Q11+'KPI_VENDEUR 3'!Q11 -> 0 | R11: =+'KPI_VENDEUR 1'!R11+'KPI_VENDEUR 2'!R11+'KPI_VENDEUR 5'!R11+'KPI_VENDEUR 4'!R11+'KPI_VENDEUR 3'!R11 -> 0 | S11: =R11/Q11 -> #DIV/0! | T11: =+'KPI_VENDEUR 1'!T11+'KPI_VENDEUR 2'!T11+'KPI_VENDEUR 5'!T11+'KPI_VENDEUR 4'!T11+'KPI_VENDEUR 3'!T11 -> 0 | U11: =+'KPI_VENDEUR 1'!U11+'KPI_VENDEUR 2'!U11+'KPI_VENDEUR 5'!U11+'KPI_VENDEUR 4'!U11+'KPI_VENDEUR 3'!U11 -> 0 | V11: =U11/T11 -> #DIV/0! | W11: =+'KPI_VENDEUR 1'!W11+'KPI_VENDEUR 2'!W11+'KPI_VENDEUR 5'!W11+'KPI_VENDEUR 4'!W11+'KPI_VENDEUR 3'!W11 -> 0 | X11: =+'KPI_VENDEUR 1'!X11+'KPI_VENDEUR 2'!X11+'KPI_VENDEUR 5'!X11+'KPI_VENDEUR 4'!X11+'KPI_VENDEUR 3'!X11 -> 0 | Y11: =X11/W11 -> #DIV/0! | Z11: =+'KPI_VENDEUR 1'!Z11+'KPI_VENDEUR 2'!Z11+'KPI_VENDEUR 5'!Z11+'KPI_VENDEUR 4'!Z11+'KPI_VENDEUR 3'!Z11 -> 0 | AA11: =+'KPI_VENDEUR 1'!AA11+'KPI_VENDEUR 2'!AA11+'KPI_VENDEUR 5'!AA11+'KPI_VENDEUR 4'!AA11+'KPI_VENDEUR 3'!AA11 -> 0 | AB11: =AA11/Z11 -> #DIV/0! | AC11: =+'KPI_VENDEUR 1'!AC11+'KPI_VENDEUR 2'!AC11+'KPI_VENDEUR 5'!AC11+'KPI_VENDEUR 4'!AC11+'KPI_VENDEUR 3'!AC11 -> 0 | AD11: =+'KPI_VENDEUR 1'!AD11+'KPI_VENDEUR 2'!AD11+'KPI_VENDEUR 5'!AD11+'KPI_VENDEUR 4'!AD11+'KPI_VENDEUR 3'!AD11 -> 0 | AE11: =AD11/AC11 -> #DIV/0! | AF11: =+'KPI_VENDEUR 1'!AF11+'KPI_VENDEUR 2'!AF11+'KPI_VENDEUR 5'!AF11+'KPI_VENDEUR 4'!AF11+'KPI_VENDEUR 3'!AF11 -> 0 | AG11: =+'KPI_VENDEUR 1'!AG11+'KPI_VENDEUR 2'!AG11+'KPI_VENDEUR 5'!AG11+'KPI_VENDEUR 4'!AG11+'KPI_VENDEUR 3'!AG11 -> 0 | AH11: =AG11/AF11 -> #DIV/0! | AI11: =+'KPI_VENDEUR 1'!AI11+'KPI_VENDEUR 2'!AI11+'KPI_VENDEUR 5'!AI11+'KPI_VENDEUR 4'!AI11+'KPI_VENDEUR 3'!AI11 -> 0 | AJ11: =+'KPI_VENDEUR 1'!AJ11+'KPI_VENDEUR 2'!AJ11+'KPI_VENDEUR 5'!AJ11+'KPI_VENDEUR 4'!AJ11+'KPI_VENDEUR 3'!AJ11 -> 0 | AK11: =AJ11/AI11 -> #DIV/0! | AL11: =+'KPI_VENDEUR 1'!AL11+'KPI_VENDEUR 2'!AL11+'KPI_VENDEUR 5'!AL11+'KPI_VENDEUR 4'!AL11+'KPI_VENDEUR 3'!AL11 -> 0 | AM11: =+'KPI_VENDEUR 1'!AM11+'KPI_VENDEUR 2'!AM11+'KPI_VENDEUR 5'!AM11+'KPI_VENDEUR 4'!AM11+'KPI_VENDEUR 3'!AM11 -> 0 | AN11: =AM11/AL11 -> #DIV/0!
A12: Nombre de Machines en stock | C12: =+'KPI_VENDEUR 1'!C12 -> #DIV/0! | F12: =+'KPI_VENDEUR 1'!F12 -> 0 | I12: =+'KPI_VENDEUR 1'!I12 -> 0 | L12: =+'KPI_VENDEUR 1'!L12 -> 0 | O12: =+'KPI_VENDEUR 1'!O12 -> 0 | R12: =+'KPI_VENDEUR 1'!R12 -> 0 | U12: =+'KPI_VENDEUR 1'!U12 -> 0 | X12: =+'KPI_VENDEUR 1'!X12 -> 0 | AA12: =+'KPI_VENDEUR 1'!AA12 -> 0 | AD12: =+'KPI_VENDEUR 1'!AD12 -> 0 | AG12: =+'KPI_VENDEUR 1'!AG12 -> 0 | AJ12: =+'KPI_VENDEUR 1'!AJ12 -> 0 | AM12: =+'KPI_VENDEUR 1'!AM12 -> 0
A13: Valeur stock Machines FCFA | C13: =+'KPI_VENDEUR 1'!C13 -> #DIV/0! | F13: =+'KPI_VENDEUR 1'!F13 -> 0 | I13: =+'KPI_VENDEUR 1'!I13 -> 0 | L13: =+'KPI_VENDEUR 1'!L13 -> 0 | O13: =+'KPI_VENDEUR 1'!O13 -> 0 | R13: =+'KPI_VENDEUR 1'!R13 -> 0 | U13: =+'KPI_VENDEUR 1'!U13 -> 0 | X13: =+'KPI_VENDEUR 1'!X13 -> 0 | AA13: =+'KPI_VENDEUR 1'!AA13 -> 0 | AD13: =+'KPI_VENDEUR 1'!AD13 -> 0 | AG13: =+'KPI_VENDEUR 1'!AG13 -> 0 | AJ13: =+'KPI_VENDEUR 1'!AJ13 -> 0 | AM13: =+'KPI_VENDEUR 1'!AM13 -> 0
E15: =+E11 -> 0 | F15: =+F11 -> 0 | G15: =F15/E15 -> #DIV/0! | H15: =+H11+E15 -> 0 | I15: =+I11+F15 -> 0 | J15: =I15/H15 -> #DIV/0! | K15: =+K11+H15 -> 0 | L15: =+L11+I15 -> 0 | M15: =L15/K15 -> #DIV/0! | N15: =+N11+K15 -> 0 | O15: =+O11+L15 -> 0 | P15: =O15/N15 -> #DIV/0! | Q15: =+Q11+N15 -> 0 | R15: =+R11+O15 -> 0 | S15: =R15/Q15 -> #DIV/0! | T15: =+T11+Q15 -> 0 | U15: =+U11+R15 -> 0 | V15: =U15/T15 -> #DIV/0! | W15: =+W11+T15 -> 0 | X15: =+X11+U15 -> 0 | Y15: =X15/W15 -> #DIV/0! | Z15: =+Z11+W15 -> 0 | AA15: =+AA11+X15 -> 0 | AB15: =AA15/Z15 -> #DIV/0! | AC15: =+AC11+Z15 -> 0 | AD15: =+AD11+AA15 -> 0 | AE15: =AD15/AC15 -> #DIV/0! | AF15: =+AF11+AC15 -> 0 | AG15: =+AG11+AD15 -> 0 | AH15: =AG15/AF15 -> #DIV/0! | AI15: =+AI11+AF15 -> 0 | AJ15: =+AJ11+AG15 -> 0 | AK15: =AJ15/AI15 -> #DIV/0!

Sheet KPI_VENDEUR 1
A1: VENDEUR 1 | B1: YTD vs B2025 | E1: 45658 | H1: 45689 | K1: 45717 | N1: 45748 | Q1: 45778 | T1: 45809 | W1: 45839 | Z1: 45870 | AC1: 45901 | AF1: 45931 | AI1: 45962 | AL1: 45992
B2: Objectif | C2: Réalisé | D2: % | E2: Objectif | F2: Réalisé | G2: % | H2: Objectif | I2: Réalisé | J2: % | K2: Objectif | L2: Réalisé | M2: % | N2: Objectif | O2: Réalisé | P2: % | Q2: Objectif | R2: Réalisé | S2: % | T2: Objectif | U2: Réalisé | V2: % | W2: Objectif | X2: Réalisé | Y2: % | Z2: Objectif | AA2: Réalisé | AB2: % | AC2: Objectif | AD2: Réalisé | AE2: % | AF2: Objectif | AG2: Réalisé | AH2: % | AI2: Objectif | AJ2: Réalisé | AK2: % | AL2: Objectif | AM2: Réalisé | AN2: %
A3: Nombre de visites clients | B3: =E3+H3+K3+N3+Q3+T3+W3+Z3+AC3+AF3+AI3+AL3 -> 0 | C3: =F3+I3+L3+O3+R3+U3+X3+AA3+AD3+AG3+AJ3+AM3 -> 0 | D3: =C3/B3 -> #DIV/0! | G3: =F3/E3 -> #DIV/0! | J3: =I3/H3 -> #DIV/0! | M3: =L3/K3 -> #DIV/0! | P3: =O3/N3 -> #DIV/0! | S3: =R3/Q3 -> #DIV/0! | V3: =U3/T3 -> #DIV/0! | Y3: =X3/W3 -> #DIV/0! | AB3: =AA3/Z3 -> #DIV/0! | AE3: =AD3/AC3 -> #DIV/0! | AH3: =AG3/AF3 -> #DIV/0! | AK3: =AJ3/AI3 -> #DIV/0! | AN3: =AM3/AL3 -> #DIV/0!
A4: Nombre d'offres commerciales | B4: =E4+H4+K4+N4+Q4+T4+W4+Z4+AC4+AF4+AI4+AL4 -> 0 | C4: =F4+I4+L4+O4+R4+U4+X4+AA4+AD4+AG4+AJ4+AM4 -> 0 | D4: =C4/B4 -> #DIV/0! | G4: =F4/E4 -> #DIV/0! | J4: =I4/H4 -> #DIV/0! | M4: =L4/K4 -> #DIV/0! | P4: =O4/N4 -> #DIV/0! | S4: =R4/Q4 -> #DIV/0! | V4: =U4/T4 -> #DIV/0! | Y4: =X4/W4 -> #DIV/0! | AB4: =AA4/Z4 -> #DIV/0! | AE4: =AD4/AC4 -> #DIV/0! | AH4: =AG4/AF4 -> #DIV/0! | AK4: =AJ4/AI4 -> #DIV/0! | AN4: =AM4/AL4 -> #DIV/0!
A5: Taux de clôture | C5: =F5+I5+L5+O5+R5+U5+X5+AA5+AD5+AG5+AJ5+AM5 -> 0 | D5: =C5/C4 -> #DIV/0! | G5: =F5/F4 -> #DIV/0! | J5: =I5/I4 -> #DIV/0! | M5: =L5/L4 -> #DIV/0! | P5: =O5/O4 -> #DIV/0! | S5: =R5/R4 -> #DIV/0! | V5: =U5/U4 -> #DIV/0! | Y5: =X5/X4 -> #DIV/0! | AB5: =AA5/AA4 -> #DIV/0! | AE5: =AD5/AD4 -> #DIV/0! | AH5: =AG5/AG4 -> #DIV/0! | AK5: =AJ5/AJ4 -> #DIV/0! | AN5: =AM5/AM4 -> #DIV/0!
A6: QTE MANITOU | B6: =E6+H6+K6+N6+Q6+T6+W6+Z6+AC6+AF6+AI6+AL6 -> 0 | C6: =F6+I6+L6+O6+R6+U6+X6+AA6+AD6+AG6+AJ6+AM6 -> 0 | D6: =C6/B6 -> #DIV/0! | G6: =F6/F5 -> #DIV/0! | J6: =I6/I5 -> #DIV/0! | M6: =L6/L5 -> #DIV/0! | P6: =O6/O5 -> #DIV/0! | S6: =R6/R5 -> #DIV/0! | V6: =U6/U5 -> #DIV/0! | Y6: =X6/X5 -> #DIV/0! | AB6: =AA6/AA5 -> #DIV/0! | AE6: =AD6/AD5 -> #DIV/0! | AH6: =AG6/AG5 -> #DIV/0! | AK6: =AJ6/AJ5 -> #DIV/0! | AN6: =AM6/AM5 -> #DIV/0!
A7: QTE KALMAR | B7: =E7+H7+K7+N7+Q7+T7+W7+Z7+AC7+AF7+AI7+AL7 -> 0 | C7: =F7+I7+L7+O7+R7+U7+X7+AA7+AD7+AG7+AJ7+AM7 -> 0 | D7: =C7/B7 -> #DIV/0! | G7: =F7/F6 -> #DIV/0! | J7: =I7/I6 -> #DIV/0! | M7: =L7/L6 -> #DIV/0! | P7: =O7/O6 -> #DIV/0! | S7: =R7/R6 -> #DIV/0! | V7: =U7/U6 -> #DIV/0! | Y7: =X7/X6 -> #DIV/0! | AB7: =AA7/AA6 -> #DIV/0! | AE7: =AD7/AD6 -> #DIV/0! | AH7: =AG7/AG6 -> #DIV/0! | AK7: =AJ7/AJ6 -> #DIV/0! | AN7: =AM7/AM6 -> #DIV/0!
A8: QTE MASSEY FERGUSON | B8: =E8+H8+K8+N8+Q8+T8+W8+Z8+AC8+AF8+AI8+AL8 -> 0 | C8: =F8+I8+L8+O8+R8+U8+X8+AA8+AD8+AG8+AJ8+AM8 -> 0 | D8: =C8/B8 -> #DIV/0! | G8: =F8/F7 -> #DIV/0! | J8: =I8/I7 -> #DIV/0! | M8: =L8/L7 -> #DIV/0! | P8: =O8/O7 -> #DIV/0! | S8: =R8/R7 -> #DIV/0! | V8: =U8/U7 -> #DIV/0! | Y8: =X8/X7 -> #DIV/0! | AB8: =AA8/AA7 -> #DIV/0! | AE8: =AD8/AD7 -> #DIV/0! | AH8: =AG8/AG7 -> #DIV/0! | AK8: =AJ8/AJ7 -> #DIV/0! | AN8: =AM8/AM7 -> #DIV/0!
A9: QTE NARDI | B9: =E9+H9+K9+N9+Q9+T9+W9+Z9+AC9+AF9+AI9+AL9 -> 0 | C9: =F9+I9+L9+O9+R9+U9+X9+AA9+AD9+AG9+AJ9+AM9 -> 0 | D9: =C9/B9 -> #DIV/0! | G9: =F9/F8 -> #DIV/0! | J9: =I9/I8 -> #DIV/0! | M9: =L9/L8 -> #DIV/0! | P9: =O9/O8 -> #DIV/0! | S9: =R9/R8 -> #DIV/0! | V9: =U9/U8 -> #DIV/0! | Y9: =X9/X8 -> #DIV/0! | AB9: =AA9/AA8 -> #DIV/0! | AE9: =AD9/AD8 -> #DIV/0! | AH9: =AG9/AG8 -> #DIV/0! | AK9: =AJ9/AJ8 -> #DIV/0! | AN9: =AM9/AM8 -> #DIV/0!
A10: QTE TOTAL VENTES | B10: =E10+H10+K10+N10+Q10+T10+W10+Z10+AC10+AF10+AI10+AL10 -> 0 | C10: =F10+I10+L10+O10+R10+U10+X10+AA10+AD10+AG10+AJ10+AM10 -> 0 | D10: =C10/B10 -> #DIV/0! | E10: =SUM(E6:E9) -> 0 | F10: =SUM(F6:F9) -> 0 | G10: =F10/E10 -> #DIV/0! | H10: =SUM(H6:H9) -> 0 | I10: =SUM(I6:I9) -> 0 | J10: =I10/H10 -> #DIV/0! | K10: =SUM(K6:K9) -> 0 | L10: =SUM(L6:L9) -> 0 | M10: =L10/K10 -> #DIV/0! | N10: =SUM(N6:N9) -> 0 | O10: =SUM(O6:O9) -> 0 | P10: =O10/N10 -> #DIV/0! | Q10: =SUM(Q6:Q9) -> 0 | R10: =SUM(R6:R9) -> 0 | S10: =R10/Q10 -> #DIV/0! | T10: =SUM(T6:T9) -> 0 | U10: =SUM(U6:U9) -> 0 | V10: =U10/T10 -> #DIV/0! | W10: =SUM(W6:W9) -> 0 | X10: =SUM(X6:X9) -> 0 | Y10: =X10/W10 -> #DIV/0! | Z10: =SUM(Z6:Z9) -> 0 | AA10: =SUM(AA6:AA9) -> 0 | AB10: =AA10/Z10 -> #DIV/0! | AC10: =SUM(AC6:AC9) -> 0 | AD10: =SUM(AD6:AD9) -> 0 | AE10: =AD10/AC10 -> #DIV/0! | AF10: =SUM(AF6:AF9) -> 0 | AG10: =SUM(AG6:AG9) -> 0 | AH10: =AG10/AF10 -> #DIV/0! | AI10: =SUM(AI6:AI9) -> 0 | AJ10: =SUM(AJ6:AJ9) -> 0 | AK10: =AJ10/AI10 -> #DIV/0! | AL10: =SUM(AL6:AL9) -> 0 | AM10: =SUM(AM6:AM9) -> 0 | AN10: =AM10/AL10 -> #DIV/0!
A11: Chiffre d'Affaires (HT) FCFA | B11: =E11+H11+K11+N11+Q11+T11+W11+Z11+AC11+AF11+AI11+AL11 -> 0 | C11: =F11+I11+L11+O11+R11+U11+X11+AA11+AD11+AG11+AJ11+AM11 -> 0 | D11: =C11/B11 -> #DIV/0! | G11: =F11/E11 -> #DIV/0! | J11: =I11/H11 -> #DIV/0! | M11: =L11/K11 -> #DIV/0! | P11: =O11/N11 -> #DIV/0! | S11: =R11/Q11 -> #DIV/0! | V11: =U11/T11 -> #DIV/0! | Y11: =X11/W11 -> #DIV/0! | AB11: =AA11/Z11 -> #DIV/0! | AE11: =AD11/AC11 -> #DIV/0! | AH11: =AG11/AF11 -> #DIV/0! | AK11: =AJ11/AI11 -> #DIV/0! | AN11: =AM11/AL11 -> #DIV/0!
A12: Nombre de Machines en stock | C12: =AVERAGE(AM12,AJ12,AG12,AD12,AA12,X12,U12,R12,O12,L12,I12,F12) -> #DIV/0!
A13: Valeur stock Machines FCFA | C13: =AVERAGE(AM13,AJ13,AG13,AD13,AA13,X13,U13,R13,O13,L13,I13,F13) -> #DIV/0!
E15: =+E11 -> 0 | F15: =+F11 -> 0 | G15: =F15/E15 -> #DIV/0! | H15: =+H11+E15 -> 0 | I15: =+I11+F15 -> 0 | J15: =I15/H15 -> #DIV/0! | K15: =+K11+H15 -> 0 | L15: =+L11+I15 -> 0 | M15: =L15/K15 -> #DIV/0! | N15: =+N11+K15 -> 0 | O15: =+O11+L15 -> 0 | P15: =O15/N15 -> #DIV/0! | Q15: =+Q11+N15 -> 0 | R15: =+R11+O15 -> 0 | S15: =R15/Q15 -> #DIV/0! | T15: =+T11+Q15 -> 0 | U15: =+U11+R15 -> 0 | V15: =U15/T15 -> #DIV/0! | W15: =+W11+T15 -> 0 | X15: =+X11+U15 -> 0 | Y15: =X15/W15 -> #DIV/0! | Z15: =+Z11+W15 -> 0 | AA15: =+AA11+X15 -> 0 | AB15: =AA15/Z15 -> #DIV/0! | AC15: =+AC11+Z15 -> 0 | AD15: =+AD11+AA15 -> 0 | AE15: =AD15/AC15 -> #DIV/0! | AF15: =+AF11+AC15 -> 0 | AG15: =+AG11+AD15 -> 0 | AH15: =AG15/AF15 -> #DIV/0! | AI15: =+AI11+AF15 -> 0 | AJ15: =+AJ11+AG15 -> 0 | AK15: =AJ15/AI15 -> #DIV/0!

Sheet KPI_VENDEUR 2
A1: VENDEUR 2 | B1: YTD vs B2025 | E1: 45658 | H1: 45689 | K1: 45717 | N1: 45748 | Q1: 45778 | T1: 45809 | W1: 45839 | Z1: 45870 | AC1: 45901 | AF1: 45931 | AI1: 45962 | AL1: 45992
B2: Objectif | C2: Réalisé | D2: % | E2: Objectif | F2: Réalisé | G2: % | H2: Objectif | I2: Réalisé | J2: % | K2: Objectif | L2: Réalisé | M2: % | N2: Objectif | O2: Réalisé | P2: % | Q2: Objectif | R2: Réalisé | S2: % | T2: Objectif | U2: Réalisé | V2: % | W2: Objectif | X2: Réalisé | Y2: % | Z2: Objectif | AA2: Réalisé | AB2: % | AC2: Objectif | AD2: Réalisé | AE2: % | AF2: Objectif | AG2: Réalisé | AH2: % | AI2: Objectif | AJ2: Réalisé | AK2: % | AL2: Objectif | AM2: Réalisé | AN2: %
A3: Nombre de visites clients | B3: =E3+H3+K3+N3+Q3+T3+W3+Z3+AC3+AF3+AI3+AL3 -> 0 | C3: =F3+I3+L3+O3+R3+U3+X3+AA3+AD3+AG3+AJ3+AM3 -> 0 | D3: =C3/B3 -> #DIV/0! | G3: =F3/E3 -> #DIV/0! | J3: =I3/H3 -> #DIV/0! | M3: =L3/K3 -> #DIV/0! | P3: =O3/N3 -> #DIV/0! | S3: =R3/Q3 -> #DIV/0! | V3: =U3/T3 -> #DIV/0! | Y3: =X3/W3 -> #DIV/0! | AB3: =AA3/Z3 -> #DIV/0! | AE3: =AD3/AC3 -> #DIV/0! | AH3: =AG3/AF3 -> #DIV/0! | AK3: =AJ3/AI3 -> #DIV/0! | AN3: =AM3/AL3 -> #DIV/0!
A4: Nombre d'offres commerciales | B4: =E4+H4+K4+N4+Q4+T4+W4+Z4+AC4+AF4+AI4+AL4 -> 0 | C4: =F4+I4+L4+O4+R4+U4+X4+AA4+AD4+AG4+AJ4+AM4 -> 0 | D4: =C4/B4 -> #DIV/0! | G4: =F4/E4 -> #DIV/0! | J4: =I4/H4 -> #DIV/0! | M4: =L4/K4 -> #DIV/0! | P4: =O4/N4 -> #DIV/0! | S4: =R4/Q4 -> #DIV/0! | V4: =U4/T4 -> #DIV/0! | Y4: =X4/W4 -> #DIV/0! | AB4: =AA4/Z4 -> #DIV/0! | AE4: =AD4/AC4 -> #DIV/0! | AH4: =AG4/AF4 -> #DIV/0! | AK4: =AJ4/AI4 -> #DIV/0! | AN4: =AM4/AL4 -> #DIV/0!
A5: Taux de clôture | C5: =F5+I5+L5+O5+R5+U5+X5+AA5+AD5+AG5+AJ5+AM5 -> 0 | D5: =C5/C4 -> #DIV/0! | G5: =F5/F4 -> #DIV/0! | J5: =I5/I4 -> #DIV/0! | M5: =L5/L4 -> #DIV/0! | P5: =O5/O4 -> #DIV/0! | S5: =R5/R4 -> #DIV/0! | V5: =U5/U4 -> #DIV/0! | Y5: =X5/X4 -> #DIV/0! | AB5: =AA5/AA4 -> #DIV/0! | AE5: =AD5/AD4 -> #DIV/0! | AH5: =AG5/AG4 -> #DIV/0! | AK5: =AJ5/AJ4 -> #DIV/0! | AN5: =AM5/AM4 -> #DIV/0!
A6: QTE MANITOU | B6: =E6+H6+K6+N6+Q6+T6+W6+Z6+AC6+AF6+AI6+AL6 -> 0 | C6: =F6+I6+L6+O6+R6+U6+X6+AA6+AD6+AG6+AJ6+AM6 -> 0 | D6: =C6/B6 -> #DIV/0! | G6: =F6/F5 -> #DIV/0! | J6: =I6/I5 -> #DIV/0! | M6: =L6/L5 -> #DIV/0! | P6: =O6/O5 -> #DIV/0! | S6: =R6/R5 -> #DIV/0! | V6: =U6/U5 -> #DIV/0! | Y6: =X6/X5 -> #DIV/0! | AB6: =AA6/AA5 -> #DIV/0! | AE6: =AD6/AD5 -> #DIV/0! | AH6: =AG6/AG5 -> #DIV/0! | AK6: =AJ6/AJ5 -> #DIV/0! | AN6: =AM6/AM5 -> #DIV/0!
A7: QTE KALMAR | B7: =E7+H7+K7+N7+Q7+T7+W7+Z7+AC7+AF7+AI7+AL7 -> 0 | C7: =F7+I7+L7+O7+R7+U7+X7+AA7+AD7+AG7+AJ7+AM7 -> 0 | D7: =C7/B7 -> #DIV/0! | G7: =F7/F6 -> #DIV/0! | J7: =I7/I6 -> #DIV/0! | M7: =L7/L6 -> #DIV/0! | P7: =O7/O6 -> #DIV/0! | S7: =R7/R6 -> #DIV/0! | V7: =U7/U6 -> #DIV/0! | Y7: =X7/X6 -> #DIV/0! | AB7: =AA7/AA6 -> #DIV/0! | AE7: =AD7/AD6 -> #DIV/0! | AH7: =AG7/AG6 -> #DIV/0! | AK7: =AJ7/AJ6 -> #DIV/0! | AN7: =AM7/AM6 -> #DIV/0!
A8: QTE MASSEY FERGUSON | B8: =E8+H8+K8+N8+Q8+T8+W8+Z8+AC8+AF8+AI8+AL8 -> 0 | C8: =F8+I8+L8+O8+R8+U8+X8+AA8+AD8+AG8+AJ8+AM8 -> 0 | D8: =C8/B8 -> #DIV/0! | G8: =F8/F7 -> #DIV/0! | J8: =I8/I7 -> #DIV/0! | M8: =L8/L7 -> #DIV/0! | P8: =O8/O7 -> #DIV/0! | S8: =R8/R7 -> #DIV/0! | V8: =U8/U7 -> #DIV/0! | Y8: =X8/X7 -> #DIV/0! | AB8: =AA8/AA7 -> #DIV/0! | AE8: =AD8/AD7 -> #DIV/0! | AH8: =AG8/AG7 -> #DIV/0! | AK8: =AJ8/AJ7 -> #DIV/0! | AN8: =AM8/AM7 -> #DIV/0!
A9: QTE NARDI | B9: =E9+H9+K9+N9+Q9+T9+W9+Z9+AC9+AF9+AI9+AL9 -> 0 | C9: =F9+I9+L9+O9+R9+U9+X9+AA9+AD9+AG9+AJ9+AM9 -> 0 | D9: =C9/B9 -> #DIV/0! | G9: =F9/F8 -> #DIV/0! | J9: =I9/I8 -> #DIV/0! | M9: =L9/L8 -> #DIV/0! | P9: =O9/O8 -> #DIV/0! | S9: =R9/R8 -> #DIV/0! | V9: =U9/U8 -> #DIV/0! | Y9: =X9/X8 -> #DIV/0! | AB9: =AA9/AA8 -> #DIV/0! | AE9: =AD9/AD8 -> #DIV/0! | AH9: =AG9/AG8 -> #DIV/0! | AK9: =AJ9/AJ8 -> #DIV/0! | AN9: =AM9/AM8 -> #DIV/0!
A10: QTE TOTAL VENTES | B10: =E10+H10+K10+N10+Q10+T10+W10+Z10+AC10+AF10+AI10+AL10 -> 0 | C10: =F10+I10+L10+O10+R10+U10+X10+AA10+AD10+AG10+AJ10+AM10 -> 0 | D10: =C10/B10 -> #DIV/0! | E10: =SUM(E6:E9) -> 0 | F10: =SUM(F6:F9) -> 0 | G10: =F10/E10 -> #DIV/0! | H10: =SUM(H6:H9) -> 0 | I10: =SUM(I6:I9) -> 0 | J10: =I10/H10 -> #DIV/0! | K10: =SUM(K6:K9) -> 0 | L10: =SUM(L6:L9) -> 0 | M10: =L10/K10 -> #DIV/0! | N10: =SUM(N6:N9) -> 0 | O10: =SUM(O6:O9) -> 0 | P10: =O10/N10 -> #DIV/0! | Q10: =SUM(Q6:Q9) -> 0 | R10: =SUM(R6:R9) -> 0 | S10: =R10/Q10 -> #DIV/0! | T10: =SUM(T6:T9) -> 0 | U10: =SUM(U6:U9) -> 0 | V10: =U10/T10 -> #DIV/0! | W10: =SUM(W6:W9) -> 0 | X10: =SUM(X6:X9) -> 0 | Y10: =X10/W10 -> #DIV/0! | Z10: =SUM(Z6:Z9) -> 0 | AA10: =SUM(AA6:AA9) -> 0 | AB10: =AA10/Z10 -> #DIV/0! | AC10: =SUM(AC6:AC9) -> 0 | AD10: =SUM(AD6:AD9) -> 0 | AE10: =AD10/AC10 -> #DIV/0! | AF10: =SUM(AF6:AF9) -> 0 | AG10: =SUM(AG6:AG9) -> 0 | AH10: =AG10/AF10 -> #DIV/0! | AI10: =SUM(AI6:AI9) -> 0 | AJ10: =SUM(AJ6:AJ9) -> 0 | AK10: =AJ10/AI10 -> #DIV/0! | AL10: =SUM(AL6:AL9) -> 0 | AM10: =SUM(AM6:AM9) -> 0 | AN10: =AM10/AL10 -> #DIV/0!
A11: Chiffre d'Affaires (HT) FCFA | B11: =E11+H11+K11+N11+Q11+T11+W11+Z11+AC11+AF11+AI11+AL11 -> 0 | C11: =F11+I11+L11+O11+R11+U11+X11+AA11+AD11+AG11+AJ11+AM11 -> 0 | D11: =C11/B11 -> #DIV/0! | G11: =F11/E11 -> #DIV/0! | J11: =I11/H11 -> #DIV/0! | M11: =L11/K11 -> #DIV/0! | P11: =O11/N11 -> #DIV/0! | S11: =R11/Q11 -> #DIV/0! | V11: =U11/T11 -> #DIV/0! | Y11: =X11/W11 -> #DIV/0! | AB11: =AA11/Z11 -> #DIV/0! | AE11: =AD11/AC11 -> #DIV/0! | AH11: =AG11/AF11 -> #DIV/0! | AK11: =AJ11/AI11 -> #DIV/0! | AN11: =AM11/AL11 -> #DIV/0!
E13: =+E11 -> 0 | F13: =+F11 -> 0 | G13: =F13/E13 -> #DIV/0! | H13: =+H11+E13 -> 0 | I13: =+I11+F13 -> 0 | J13: =I13/H13 -> #DIV/0! | K13: =+K11+H13 -> 0 | L13: =+L11+I13 -> 0 | M13: =L13/K13 -> #DIV/0! | N13: =+N11+K13 -> 0 | O13: =+O11+L13 -> 0 | P13: =O13/N13 -> #DIV/0! | Q13: =+Q11+N13 -> 0 | R13: =+R11+O13 -> 0 | S13: =R13/Q13 -> #DIV/0! | T13: =+T11+Q13 -> 0 | U13: =+U11+R13 -> 0 | V13: =U13/T13 -> #DIV/0! | W13: =+W11+T13 -> 0 | X13: =+X11+U13 -> 0 | Y13: =X13/W13 -> #DIV/0! | Z13: =+Z11+W13 -> 0 | AA13: =+AA11+X13 -> 0 | AB13: =AA13/Z13 -> #DIV/0! | AC13: =+AC11+Z13 -> 0 | AD13: =+AD11+AA13 -> 0 | AE13: =AD13/AC13 -> #DIV/0! | AF13: =+AF11+AC13 -> 0 | AG13: =+AG11+AD13 -> 0 | AH13: =AG13/AF13 -> #DIV/0! | AI13: =+AI11+AF13 -> 0 | AJ13: =+AJ11+AG13 -> 0 | AK13: =AJ13/AI13 -> #DIV/0!

Sheet KPI_VENDEUR 3
A1: VENDEUR 3 | B1: YTD vs B2025 | E1: 45658 | H1: 45689 | K1: 45717 | N1: 45748 | Q1: 45778 | T1: 45809 | W1: 45839 | Z1: 45870 | AC1: 45901 | AF1: 45931 | AI1: 45962 | AL1: 45992
B2: Objectif | C2: Réalisé | D2: % | E2: Objectif | F2: Réalisé | G2: % | H2: Objectif | I2: Réalisé | J2: % | K2: Objectif | L2: Réalisé | M2: % | N2: Objectif | O2: Réalisé | P2: % | Q2: Objectif | R2: Réalisé | S2: % | T2: Objectif | U2: Réalisé | V2: % | W2: Objectif | X2: Réalisé | Y2: % | Z2: Objectif | AA2: Réalisé | AB2: % | AC2: Objectif | AD2: Réalisé | AE2: % | AF2: Objectif | AG2: Réalisé | AH2: % | AI2: Objectif | AJ2: Réalisé | AK2: % | AL2: Objectif | AM2: Réalisé | AN2: %
A3: Nombre de visites clients | B3: =E3+H3+K3+N3+Q3+T3+W3+Z3+AC3+AF3+AI3+AL3 -> 0 | C3: =F3+I3+L3+O3+R3+U3+X3+AA3+AD3+AG3+AJ3+AM3 -> 0 | D3: =C3/B3 -> #DIV/0! | G3: =F3/E3 -> #DIV/0! | J3: =I3/H3 -> #DIV/0! | M3: =L3/K3 -> #DIV/0! | P3: =O3/N3 -> #DIV/0! | S3: =R3/Q3 -> #DIV/0! | V3: =U3/T3 -> #DIV/0! | Y3: =X3/W3 -> #DIV/0! | AB3: =AA3/Z3 -> #DIV/0! | AE3: =AD3/AC3 -> #DIV/0! | AH3: =AG3/AF3 -> #DIV/0! | AK3: =AJ3/AI3 -> #DIV/0! | AN3: =AM3/AL3 -> #DIV/0!
A4: Nombre d'offres commerciales | B4: =E4+H4+K4+N4+Q4+T4+W4+Z4+AC4+AF4+AI4+AL4 -> 0 | C4: =F4+I4+L4+O4+R4+U4+X4+AA4+AD4+AG4+AJ4+AM4 -> 0 | D4: =C4/B4 -> #DIV/0! | G4: =F4/E4 -> #DIV/0! | J4: =I4/H4 -> #DIV/0! | M4: =L4/K4 -> #DIV/0! | P4: =O4/N4 -> #DIV/0! | S4: =R4/Q4 -> #DIV/0! | V4: =U4/T4 -> #DIV/0! | Y4: =X4/W4 -> #DIV/0! | AB4: =AA4/Z4 -> #DIV/0! | AE4: =AD4/AC4 -> #DIV/0! | AH4: =AG4/AF4 -> #DIV/0! | AK4: =AJ4/AI4 -> #DIV/0! | AN4: =AM4/AL4 -> #DIV/0!
A5: Taux de clôture | C5: =F5+I5+L5+O5+R5+U5+X5+AA5+AD5+AG5+AJ5+AM5 -> 0 | D5: =C5/C4 -> #DIV/0! | G5: =F5/F4 -> #DIV/0! | J5: =I5/I4 -> #DIV/0! | M5: =L5/L4 -> #DIV/0! | P5: =O5/O4 -> #DIV/0! | S5: =R5/R4 -> #DIV/0! | V5: =U5/U4 -> #DIV/0! | Y5: =X5/X4 -> #DIV/0! | AB5: =AA5/AA4 -> #DIV/0! | AE5: =AD5/AD4 -> #DIV/0! | AH5: =AG5/AG4 -> #DIV/0! | AK5: =AJ5/AJ4 -> #DIV/0! | AN5: =AM5/AM4 -> #DIV/0!
A6: QTE MANITOU | B6: =E6+H6+K6+N6+Q6+T6+W6+Z6+AC6+AF6+AI6+AL6 -> 0 | C6: =F6+I6+L6+O6+R6+U6+X6+AA6+AD6+AG6+AJ6+AM6 -> 0 | D6: =C6/B6 -> #DIV/0! | G6: =F6/F5 -> #DIV/0! | J6: =I6/I5 -> #DIV/0! | M6: =L6/L5 -> #DIV/0! | P6: =O6/O5 -> #DIV/0! | S6: =R6/R5 -> #DIV/0! | V6: =U6/U5 -> #DIV/0! | Y6: =X6/X5 -> #DIV/0! | AB6: =AA6/AA5 -> #DIV/0! | AE6: =AD6/AD5 -> #DIV/0! | AH6: =AG6/AG5 -> #DIV/0! | AK6: =AJ6/AJ5 -> #DIV/0! | AN6: =AM6/AM5 -> #DIV/0!
A7: QTE KALMAR | B7: =E7+H7+K7+N7+Q7+T7+W7+Z7+AC7+AF7+AI7+AL7 -> 0 | C7: =F7+I7+L7+O7+R7+U7+X7+AA7+AD7+AG7+AJ7+AM7 -> 0 | D7: =C7/B7 -> #DIV/0! | G7: =F7/F6 -> #DIV/0! | J7: =I7/I6 -> #DIV/0! | M7: =L7/L6 -> #DIV/0! | P7: =O7/O6 -> #DIV/0! | S7: =R7/R6 -> #DIV/0! | V7: =U7/U6 -> #DIV/0! | Y7: =X7/X6 -> #DIV/0! | AB7: =AA7/AA6 -> #DIV/0! | AE7: =AD7/AD6 -> #DIV/0! | AH7: =AG7/AG6 -> #DIV/0! | AK7: =AJ7/AJ6 -> #DIV/0! | AN7: =AM7/AM6 -> #DIV/0!
A8: QTE MASSEY FERGUSON | B8: =E8+H8+K8+N8+Q8+T8+W8+Z8+AC8+AF8+AI8+AL8 -> 0 | C8: =F8+I8+L8+O8+R8+U8+X8+AA8+AD8+AG8+AJ8+AM8 -> 0 | D8: =C8/B8 -> #DIV/0! | G8: =F8/F7 -> #DIV/0! | J8: =I8/I7 -> #DIV/0! | M8: =L8/L7 -> #DIV/0! | P8: =O8/O7 -> #DIV/0! | S8: =R8/R7 -> #DIV/0! | V8: =U8/U7 -> #DIV/0! | Y8: =X8/X7 -> #DIV/0! | AB8: =AA8/AA7 -> #DIV/0! | AE8: =AD8/AD7 -> #DIV/0! | AH8: =AG8/AG7 -> #DIV/0! | AK8: =AJ8/AJ7 -> #DIV/0! | AN8: =AM8/AM7 -> #DIV/0!
A9: QTE NARDI | B9: =E9+H9+K9+N9+Q9+T9+W9+Z9+AC9+AF9+AI9+AL9 -> 0 | C9: =F9+I9+L9+O9+R9+U9+X9+AA9+AD9+AG9+AJ9+AM9 -> 0 | D9: =C9/B9 -> #DIV/0! | G9: =F9/F8 -> #DIV/0! | J9: =I9/I8 -> #DIV/0! | M9: =L9/L8 -> #DIV/0! | P9: =O9/O8 -> #DIV/0! | S9: =R9/R8 -> #DIV/0! | V9: =U9/U8 -> #DIV/0! | Y9: =X9/X8 -> #DIV/0! | AB9: =AA9/AA8 -> #DIV/0! | AE9: =AD9/AD8 -> #DIV/0! | AH9: =AG9/AG8 -> #DIV/0! | AK9: =AJ9/AJ8 -> #DIV/0! | AN9: =AM9/AM8 -> #DIV/0!
A10: QTE TOTAL VENTES | B10: =E10+H10+K10+N10+Q10+T10+W10+Z10+AC10+AF10+AI10+AL10 -> 0 | C10: =F10+I10+L10+O10+R10+U10+X10+AA10+AD10+AG10+AJ10+AM10 -> 0 | D10: =C10/B10 -> #DIV/0! | E10: =SUM(E6:E9) -> 0 | F10: =SUM(F6:F9) -> 0 | G10: =F10/E10 -> #DIV/0! | H10: =SUM(H6:H9) -> 0 | I10: =SUM(I6:I9) -> 0 | J10: =I10/H10 -> #DIV/0! | K10: =SUM(K6:K9) -> 0 | L10: =SUM(L6:L9) -> 0 | M10: =L10/K10 -> #DIV/0! | N10: =SUM(N6:N9) -> 0 | O10: =SUM(O6:O9) -> 0 | P10: =O10/N10 -> #DIV/0! | Q10: =SUM(Q6:Q9) -> 0 | R10: =SUM(R6:R9) -> 0 | S10: =R10/Q10 -> #DIV/0! | T10: =SUM(T6:T9) -> 0 | U10: =SUM(U6:U9) -> 0 | V10: =U10/T10 -> #DIV/0! | W10: =SUM(W6:W9) -> 0 | X10: =SUM(X6:X9) -> 0 | Y10: =X10/W10 -> #DIV/0! | Z10: =SUM(Z6:Z9) -> 0 | AA10: =SUM(AA6:AA9) -> 0 | AB10: =AA10/Z10 -> #DIV/0! | AC10: =SUM(AC6:AC9) -> 0 | AD10: =SUM(AD6:AD9) -> 0 | AE10: =AD10/AC10 -> #DIV/0! | AF10: =SUM(AF6:AF9) -> 0 | AG10: =SUM(AG6:AG9) -> 0 | AH10: =AG10/AF10 -> #DIV/0! | AI10: =SUM(AI6:AI9) -> 0 | AJ10: =SUM(AJ6:AJ9) -> 0 | AK10: =AJ10/AI10 -> #DIV/0! | AL10: =SUM(AL6:AL9) -> 0 | AM10: =SUM(AM6:AM9) -> 0 | AN10: =AM10/AL10 -> #DIV/0!
A11: Chiffre d'Affaires (HT) FCFA | B11: =E11+H11+K11+N11+Q11+T11+W11+Z11+AC11+AF11+AI11+AL11 -> 0 | C11: =F11+I11+L11+O11+R11+U11+X11+AA11+AD11+AG11+AJ11+AM11 -> 0 | D11: =C11/B11 -> #DIV/0! | G11: =F11/E11 -> #DIV/0! | J11: =I11/H11 -> #DIV/0! | M11: =L11/K11 -> #DIV/0! | P11: =O11/N11 -> #DIV/0! | S11: =R11/Q11 -> #DIV/0! | V11: =U11/T11 -> #DIV/0! | Y11: =X11/W11 -> #DIV/0! | AB11: =AA11/Z11 -> #DIV/0! | AE11: =AD11/AC11 -> #DIV/0! | AH11: =AG11/AF11 -> #DIV/0! | AK11: =AJ11/AI11 -> #DIV/0! | AN11: =AM11/AL11 -> #DIV/0!
E13: =+E11 -> 0 | F13: =+F11 -> 0 | G13: =F13/E13 -> #DIV/0! | H13: =+H11+E13 -> 0 | I13: =+I11+F13 -> 0 | J13: =I13/H13 -> #DIV/0! | K13: =+K11+H13 -> 0 | L13: =+L11+I13 -> 0 | M13: =L13/K13 -> #DIV/0! | N13: =+N11+K13 -> 0 | O13: =+O11+L13 -> 0 | P13: =O13/N13 -> #DIV/0! | Q13: =+Q11+N13 -> 0 | R13: =+R11+O13 -> 0 | S13: =R13/Q13 -> #DIV/0! | T13: =+T11+Q13 -> 0 | U13: =+U11+R13 -> 0 | V13: =U13/T13 -> #DIV/0! | W13: =+W11+T13 -> 0 | X13: =+X11+U13 -> 0 | Y13: =X13/W13 -> #DIV/0! | Z13: =+Z11+W13 -> 0 | AA13: =+AA11+X13 -> 0 | AB13: =AA13/Z13 -> #DIV/0! | AC13: =+AC11+Z13 -> 0 | AD13: =+AD11+AA13 -> 0 | AE13: =AD13/AC13 -> #DIV/0! | AF13: =+AF11+AC13 -> 0 | AG13: =+AG11+AD13 -> 0 | AH13: =AG13/AF13 -> #DIV/0! | AI13: =+AI11+AF13 -> 0 | AJ13: =+AJ11+AG13 -> 0 | AK13: =AJ13/AI13 -> #DIV/0!

Sheet KPI_VENDEUR 4
A1: VENDEUR 4 | B1: YTD vs B2025 | E1: 45658 | H1: 45689 | K1: 45717 | N1: 45748 | Q1: 45778 | T1: 45809 | W1: 45839 | Z1: 45870 | AC1: 45901 | AF1: 45931 | AI1: 45962 | AL1: 45992
B2: Objectif | C2: Réalisé | D2: % | E2: Objectif | F2: Réalisé | G2: % | H2: Objectif | I2: Réalisé | J2: % | K2: Objectif | L2: Réalisé | M2: % | N2: Objectif | O2: Réalisé | P2: % | Q2: Objectif | R2: Réalisé | S2: % | T2: Objectif | U2: Réalisé | V2: % | W2: Objectif | X2: Réalisé | Y2: % | Z2: Objectif | AA2: Réalisé | AB2: % | AC2: Objectif | AD2: Réalisé | AE2: % | AF2: Objectif | AG2: Réalisé | AH2: % | AI2: Objectif | AJ2: Réalisé | AK2: % | AL2: Objectif | AM2: Réalisé | AN2: %
A3: Nombre de visites clients | B3: =E3+H3+K3+N3+Q3+T3+W3+Z3+AC3+AF3+AI3+AL3 -> 0 | C3: =F3+I3+L3+O3+R3+U3+X3+AA3+AD3+AG3+AJ3+AM3 -> 0 | D3: =C3/B3 -> #DIV/0! | G3: =F3/E3 -> #DIV/0! | J3: =I3/H3 -> #DIV/0! | M3: =L3/K3 -> #DIV/0! | P3: =O3/N3 -> #DIV/0! | S3: =R3/Q3 -> #DIV/0! | V3: =U3/T3 -> #DIV/0! | Y3: =X3/W3 -> #DIV/0! | AB3: =AA3/Z3 -> #DIV/0! | AE3: =AD3/AC3 -> #DIV/0! | AH3: =AG3/AF3 -> #DIV/0! | AK3: =AJ3/AI3 -> #DIV/0! | AN3: =AM3/AL3 -> #DIV/0!
A4: Nombre d'offres commerciales | B4: =E4+H4+K4+N4+Q4+T4+W4+Z4+AC4+AF4+AI4+AL4 -> 0 | C4: =F4+I4+L4+O4+R4+U4+X4+AA4+AD4+AG4+AJ4+AM4 -> 0 | D4: =C4/B4 -> #DIV/0! | G4: =F4/E4 -> #DIV/0! | J4: =I4/H4 -> #DIV/0! | M4: =L4/K4 -> #DIV/0! | P4: =O4/N4 -> #DIV/0! | S4: =R4/Q4 -> #DIV/0! | V4: =U4/T4 -> #DIV/0! | Y4: =X4/W4 -> #DIV/0! | AB4: =AA4/Z4 -> #DIV/0! | AE4: =AD4/AC4 -> #DIV/0! | AH4: =AG4/AF4 -> #DIV/0! | AK4: =AJ4/AI4 -> #DIV/0! | AN4: =AM4/AL4 -> #DIV/0!
A5: Taux de clôture | C5: =F5+I5+L5+O5+R5+U5+X5+AA5+AD5+AG5+AJ5+AM5 -> 0 | D5: =C5/C4 -> #DIV/0! | G5: =F5/F4 -> #DIV/0! | J5: =I5/I4 -> #DIV/0! | M5: =L5/L4 -> #DIV/0! | P5: =O5/O4 -> #DIV/0! | S5: =R5/R4 -> #DIV/0! | V5: =U5/U4 -> #DIV/0! | Y5: =X5/X4 -> #DIV/0! | AB5: =AA5/AA4 -> #DIV/0! | AE5: =AD5/AD4 -> #DIV/0! | AH5: =AG5/AG4 -> #DIV/0! | AK5: =AJ5/AJ4 -> #DIV/0! | AN5: =AM5/AM4 -> #DIV/0!
A6: QTE MANITOU | B6: =E6+H6+K6+N6+Q6+T6+W6+Z6+AC6+AF6+AI6+AL6 -> 0 | C6: =F6+I6+L6+O6+R6+U6+X6+AA6+AD6+AG6+AJ6+AM6 -> 0 | D6: =C6/B6 -> #DIV/0! | G6: =F6/F5 -> #DIV/0! | J6: =I6/I5 -> #DIV/0! | M6: =L6/L5 -> #DIV/0! | P6: =O6/O5 -> #DIV/0! | S6: =R6/R5 -> #DIV/0! | V6: =U6/U5 -> #DIV/0! | Y6: =X6/X5 -> #DIV/0! | AB6: =AA6/AA5 -> #DIV/0! | AE6: =AD6/AD5 -> #DIV/0! | AH6: =AG6/AG5 -> #DIV/0! | AK6: =AJ6/AJ5 -> #DIV/0! | AN6: =AM6/AM5 -> #DIV/0!
A7: QTE KALMAR | B7: =E7+H7+K7+N7+Q7+T7+W7+Z7+AC7+AF7+AI7+AL7 -> 0 | C7: =F7+I7+L7+O7+R7+U7+X7+AA7+AD7+AG7+AJ7+AM7 -> 0 | D7: =C7/B7 -> #DIV/0! | G7: =F7/F6 -> #DIV/0! | J7: =I7/I6 -> #DIV/0! | M7: =L7/L6 -> #DIV/0! | P7: =O7/O6 -> #DIV/0! | S7: =R7/R6 -> #DIV/0! | V7: =U7/U6 -> #DIV/0! | Y7: =X7/X6 -> #DIV/0! | AB7: =AA7/AA6 -> #DIV/0! | AE7: =AD7/AD6 -> #DIV/0! | AH7: =AG7/AG6 -> #DIV/0! | AK7: =AJ7/AJ6 -> #DIV/0! | AN7: =AM7/AM6 -> #DIV/0!
A8: QTE MASSEY FERGUSON | B8: =E8+H8+K8+N8+Q8+T8+W8+Z8+AC8+AF8+AI8+AL8 -> 0 | C8: =F8+I8+L8+O8+R8+U8+X8+AA8+AD8+AG8+AJ8+AM8 -> 0 | D8: =C8/B8 -> #DIV/0! | G8: =F8/F7 -> #DIV/0! | J8: =I8/I7 -> #DIV/0! | M8: =L8/L7 -> #DIV/0! | P8: =O8/O7 -> #DIV/0! | S8: =R8/R7 -> #DIV/0! | V8: =U8/U7 -> #DIV/0! | Y8: =X8/X7 -> #DIV/0! | AB8: =AA8/AA7 -> #DIV/0! | AE8: =AD8/AD7 -> #DIV/0! | AH8: =AG8/AG7 -> #DIV/0! | AK8: =AJ8/AJ7 -> #DIV/0! | AN8: =AM8/AM7 -> #DIV/0!
A9: QTE NARDI | B9: =E9+H9+K9+N9+Q9+T9+W9+Z9+AC9+AF9+AI9+AL9 -> 0 | C9: =F9+I9+L9+O9+R9+U9+X9+AA9+AD9+AG9+AJ9+AM9 -> 0 | D9: =C9/B9 -> #DIV/0! | G9: =F9/F8 -> #DIV/0! | J9: =I9/I8 -> #DIV/0! | M9: =L9/L8 -> #DIV/0! | P9: =O9/O8 -> #DIV/0! | S9: =R9/R8 -> #DIV/0! | V9: =U9/U8 -> #DIV/0! | Y9: =X9/X8 -> #DIV/0! | AB9: =AA9/AA8 -> #DIV/0! | AE9: =AD9/AD8 -> #DIV/0! | AH9: =AG9/AG8 -> #DIV/0! | AK9: =AJ9/AJ8 -> #DIV/0! | AN9: =AM9/AM8 -> #DIV/0!
A10: QTE TOTAL VENTES | B10: =E10+H10+K10+N10+Q10+T10+W10+Z10+AC10+AF10+AI10+AL10 -> 0 | C10: =F10+I10+L10+O10+R10+U10+X10+AA10+AD10+AG10+AJ10+AM10 -> 0 | D10: =C10/B10 -> #DIV/0! | E10: =SUM(E6:E9) -> 0 | F10: =SUM(F6:F9) -> 0 | G10: =F10/E10 -> #DIV/0! | H10: =SUM(H6:H9) -> 0 | I10: =SUM(I6:I9) -> 0 | J10: =I10/H10 -> #DIV/0! | K10: =SUM(K6:K9) -> 0 | L10: =SUM(L6:L9) -> 0 | M10: =L10/K10 -> #DIV/0! | N10: =SUM(N6:N9) -> 0 | O10: =SUM(O6:O9) -> 0 | P10: =O10/N10 -> #DIV/0! | Q10: =SUM(Q6:Q9) -> 0 | R10: =SUM(R6:R9) -> 0 | S10: =R10/Q10 -> #DIV/0! | T10: =SUM(T6:T9) -> 0 | U10: =SUM(U6:U9) -> 0 | V10: =U10/T10 -> #DIV/0! | W10: =SUM(W6:W9) -> 0 | X10: =SUM(X6:X9) -> 0 | Y10: =X10/W10 -> #DIV/0! | Z10: =SUM(Z6:Z9) -> 0 | AA10: =SUM(AA6:AA9) -> 0 | AB10: =AA10/Z10 -> #DIV/0! | AC10: =SUM(AC6:AC9) -> 0 | AD10: =SUM(AD6:AD9) -> 0 | AE10: =AD10/AC10 -> #DIV/0! | AF10: =SUM(AF6:AF9) -> 0 | AG10: =SUM(AG6:AG9) -> 0 | AH10: =AG10/AF10 -> #DIV/0! | AI10: =SUM(AI6:AI9) -> 0 | AJ10: =SUM(AJ6:AJ9) -> 0 | AK10: =AJ10/AI10 -> #DIV/0! | AL10: =SUM(AL6:AL9) -> 0 | AM10: =SUM(AM6:AM9) -> 0 | AN10: =AM10/AL10 -> #DIV/0!
A11: Chiffre d'Affaires (HT) FCFA | B11: =E11+H11+K11+N11+Q11+T11+W11+Z11+AC11+AF11+AI11+AL11 -> 0 | C11: =F11+I11+L11+O11+R11+U11+X11+AA11+AD11+AG11+AJ11+AM11 -> 0 | D11: =C11/B11 -> #DIV/0! | G11: =F11/E11 -> #DIV/0! | J11: =I11/H11 -> #DIV/0! | M11: =L11/K11 -> #DIV/0! | P11: =O11/N11 -> #DIV/0! | S11: =R11/Q11 -> #DIV/0! | V11: =U11/T11 -> #DIV/0! | Y11: =X11/W11 -> #DIV/0! | AB11: =AA11/Z11 -> #DIV/0! | AE11: =AD11/AC11 -> #DIV/0! | AH11: =AG11/AF11 -> #DIV/0! | AK11: =AJ11/AI11 -> #DIV/0! | AN11: =AM11/AL11 -> #DIV/0!
E13: =+E11 -> 0 | F13: =+F11 -> 0 | G13: =F13/E13 -> #DIV/0! | H13: =+H11+E13 -> 0 | I13: =+I11+F13 -> 0 | J13: =I13/H13 -> #DIV/0! | K13: =+K11+H13 -> 0 | L13: =+L11+I13 -> 0 | M13: =L13/K13 -> #DIV/0! | N13: =+N11+K13 -> 0 | O13: =+O11+L13 -> 0 | P13: =O13/N13 -> #DIV/0! | Q13: =+Q11+N13 -> 0 | R13: =+R11+O13 -> 0 | S13: =R13/Q13 -> #DIV/0! | T13: =+T11+Q13 -> 0 | U13: =+U11+R13 -> 0 | V13: =U13/T13 -> #DIV/0! | W13: =+W11+T13 -> 0 | X13: =+X11+U13 -> 0 | Y13: =X13/W13 -> #DIV/0! | Z13: =+Z11+W13 -> 0 | AA13: =+AA11+X13 -> 0 | AB13: =AA13/Z13 -> #DIV/0! | AC13: =+AC11+Z13 -> 0 | AD13: =+AD11+AA13 -> 0 | AE13: =AD13/AC13 -> #DIV/0! | AF13: =+AF11+AC13 -> 0 | AG13: =+AG11+AD13 -> 0 | AH13: =AG13/AF13 -> #DIV/0! | AI13: =+AI11+AF13 -> 0 | AJ13: =+AJ11+AG13 -> 0 | AK13: =AJ13/AI13 -> #DIV/0!

Sheet KPI_VENDEUR 5
A1: VENDEUR 5 | B1: YTD vs B2025 | E1: 45658 | H1: 45689 | K1: 45717 | N1: 45748 | Q1: 45778 | T1: 45809 | W1: 45839 | Z1: 45870 | AC1: 45901 | AF1: 45931 | AI1: 45962 | AL1: 45992
B2: Objectif | C2: Réalisé | D2: % | E2: Objectif | F2: Réalisé | G2: % | H2: Objectif | I2: Réalisé | J2: % | K2: Objectif | L2: Réalisé | M2: % | N2: Objectif | O2: Réalisé | P2: % | Q2: Objectif | R2: Réalisé | S2: % | T2: Objectif | U2: Réalisé | V2: % | W2: Objectif | X2: Réalisé | Y2: % | Z2: Objectif | AA2: Réalisé | AB2: % | AC2: Objectif | AD2: Réalisé | AE2: % | AF2: Objectif | AG2: Réalisé | AH2: % | AI2: Objectif | AJ2: Réalisé | AK2: % | AL2: Objectif | AM2: Réalisé | AN2: %
A3: Nombre de visites clients | B3: =E3+H3+K3+N3+Q3+T3+W3+Z3+AC3+AF3+AI3+AL3 -> 0 | C3: =F3+I3+L3+O3+R3+U3+X3+AA3+AD3+AG3+AJ3+AM3 -> 0 | D3: =C3/B3 -> #DIV/0! | G3: =F3/E3 -> #DIV/0! | J3: =I3/H3 -> #DIV/0! | M3: =L3/K3 -> #DIV/0! | P3: =O3/N3 -> #DIV/0! | S3: =R3/Q3 -> #DIV/0! | V3: =U3/T3 -> #DIV/0! | Y3: =X3/W3 -> #DIV/0! | AB3: =AA3/Z3 -> #DIV/0! | AE3: =AD3/AC3 -> #DIV/0! | AH3: =AG3/AF3 -> #DIV/0! | AK3: =AJ3/AI3 -> #DIV/0! | AN3: =AM3/AL3 -> #DIV/0!
A4: Nombre d'offres commerciales | B4: =E4+H4+K4+N4+Q4+T4+W4+Z4+AC4+AF4+AI4+AL4 -> 0 | C4: =F4+I4+L4+O4+R4+U4+X4+AA4+AD4+AG4+AJ4+AM4 -> 0 | D4: =C4/B4 -> #DIV/0! | G4: =F4/E4 -> #DIV/0! | J4: =I4/H4 -> #DIV/0! | M4: =L4/K4 -> #DIV/0! | P4: =O4/N4 -> #DIV/0! | S4: =R4/Q4 -> #DIV/0! | V4: =U4/T4 -> #DIV/0! | Y4: =X4/W4 -> #DIV/0! | AB4: =AA4/Z4 -> #DIV/0! | AE4: =AD4/AC4 -> #DIV/0! | AH4: =AG4/AF4 -> #DIV/0! | AK4: =AJ4/AI4 -> #DIV/0! | AN4: =AM4/AL4 -> #DIV/0!
A5: Taux de clôture | C5: =F5+I5+L5+O5+R5+U5+X5+AA5+AD5+AG5+AJ5+AM5 -> 0 | D5: =C5/C4 -> #DIV/0! | G5: =F5/F4 -> #DIV/0! | J5: =I5/I4 -> #DIV/0! | M5: =L5/L4 -> #DIV/0! | P5: =O5/O4 -> #DIV/0! | S5: =R5/R4 -> #DIV/0! | V5: =U5/U4 -> #DIV/0! | Y5: =X5/X4 -> #DIV/0! | AB5: =AA5/AA4 -> #DIV/0! | AE5: =AD5/AD4 -> #DIV/0! | AH5: =AG5/AG4 -> #DIV/0! | AK5: =AJ5/AJ4 -> #DIV/0! | AN5: =AM5/AM4 -> #DIV/0!
A6: QTE MANITOU | B6: =E6+H6+K6+N6+Q6+T6+W6+Z6+AC6+AF6+AI6+AL6 -> 0 | C6: =F6+I6+L6+O6+R6+U6+X6+AA6+AD6+AG6+AJ6+AM6 -> 0 | D6: =C6/B6 -> #DIV/0! | G6: =F6/F5 -> #DIV/0! | J6: =I6/I5 -> #DIV/0! | M6: =L6/L5 -> #DIV/0! | P6: =O6/O5 -> #DIV/0! | S6: =R6/R5 -> #DIV/0! | V6: =U6/U5 -> #DIV/0! | Y6: =X6/X5 -> #DIV/0! | AB6: =AA6/AA5 -> #DIV/0! | AE6: =AD6/AD5 -> #DIV/0! | AH6: =AG6/AG5 -> #DIV/0! | AK6: =AJ6/AJ5 -> #DIV/0! | AN6: =AM6/AM5 -> #DIV/0!
A7: QTE KALMAR | B7: =E7+H7+K7+N7+Q7+T7+W7+Z7+AC7+AF7+AI7+AL7 -> 0 | C7: =F7+I7+L7+O7+R7+U7+X7+AA7+AD7+AG7+AJ7+AM7 -> 0 | D7: =C7/B7 -> #DIV/0! | G7: =F7/F6 -> #DIV/0! | J7: =I7/I6 -> #DIV/0! | M7: =L7/L6 -> #DIV/0! | P7: =O7/O6 -> #DIV/0! | S7: =R7/R6 -> #DIV/0! | V7: =U7/U6 -> #DIV/0! | Y7: =X7/X6 -> #DIV/0! | AB7: =AA7/AA6 -> #DIV/0! | AE7: =AD7/AD6 -> #DIV/0! | AH7: =AG7/AG6 -> #DIV/0! | AK7: =AJ7/AJ6 -> #DIV/0! | AN7: =AM7/AM6 -> #DIV/0!
A8: QTE MASSEY FERGUSON | B8: =E8+H8+K8+N8+Q8+T8+W8+Z8+AC8+AF8+AI8+AL8 -> 0 | C8: =F8+I8+L8+O8+R8+U8+X8+AA8+AD8+AG8+AJ8+AM8 -> 0 | D8: =C8/B8 -> #DIV/0! | G8: =F8/F7 -> #DIV/0! | J8: =I8/I7 -> #DIV/0! | M8: =L8/L7 -> #DIV/0! | P8: =O8/O7 -> #DIV/0! | S8: =R8/R7 -> #DIV/0! | V8: =U8/U7 -> #DIV/0! | Y8: =X8/X7 -> #DIV/0! | AB8: =AA8/AA7 -> #DIV/0! | AE8: =AD8/AD7 -> #DIV/0! | AH8: =AG8/AG7 -> #DIV/0! | AK8: =AJ8/AJ7 -> #DIV/0! | AN8: =AM8/AM7 -> #DIV/0!
A9: QTE NARDI | B9: =E9+H9+K9+N9+Q9+T9+W9+Z9+AC9+AF9+AI9+AL9 -> 0 | C9: =F9+I9+L9+O9+R9+U9+X9+AA9+AD9+AG9+AJ9+AM9 -> 0 | D9: =C9/B9 -> #DIV/0! | G9: =F9/F8 -> #DIV/0! | J9: =I9/I8 -> #DIV/0! | M9: =L9/L8 -> #DIV/0! | P9: =O9/O8 -> #DIV/0! | S9: =R9/R8 -> #DIV/0! | V9: =U9/U8 -> #DIV/0! | Y9: =X9/X8 -> #DIV/0! | AB9: =AA9/AA8 -> #DIV/0! | AE9: =AD9/AD8 -> #DIV/0! | AH9: =AG9/AG8 -> #DIV/0! | AK9: =AJ9/AJ8 -> #DIV/0! | AN9: =AM9/AM8 -> #DIV/0!
A10: QTE TOTAL VENTES | B10: =E10+H10+K10+N10+Q10+T10+W10+Z10+AC10+AF10+AI10+AL10 -> 0 | C10: =F10+I10+L10+O10+R10+U10+X10+AA10+AD10+AG10+AJ10+AM10 -> 0 | D10: =C10/B10 -> #DIV/0! | E10: =SUM(E6:E9) -> 0 | F10: =SUM(F6:F9) -> 0 | G10: =F10/E10 -> #DIV/0! | H10: =SUM(H6:H9) -> 0 | I10: =SUM(I6:I9) -> 0 | J10: =I10/H10 -> #DIV/0! | K10: =SUM(K6:K9) -> 0 | L10: =SUM(L6:L9) -> 0 | M10: =L10/K10 -> #DIV/0! | N10: =SUM(N6:N9) -> 0 | O10: =SUM(O6:O9) -> 0 | P10: =O10/N10 -> #DIV/0! | Q10: =SUM(Q6:Q9) -> 0 | R10: =SUM(R6:R9) -> 0 | S10: =R10/Q10 -> #DIV/0! | T10: =SUM(T6:T9) -> 0 | U10: =SUM(U6:U9) -> 0 | V10: =U10/T10 -> #DIV/0! | W10: =SUM(W6:W9) -> 0 | X10: =SUM(X6:X9) -> 0 | Y10: =X10/W10 -> #DIV/0! | Z10: =SUM(Z6:Z9) -> 0 | AA10: =SUM(AA6:AA9) -> 0 | AB10: =AA10/Z10 -> #DIV/0! | AC10: =SUM(AC6:AC9) -> 0 | AD10: =SUM(AD6:AD9) -> 0 | AE10: =AD10/AC10 -> #DIV/0! | AF10: =SUM(AF6:AF9) -> 0 | AG10: =SUM(AG6:AG9) -> 0 | AH10: =AG10/AF10 -> #DIV/0! | AI10: =SUM(AI6:AI9) -> 0 | AJ10: =SUM(AJ6:AJ9) -> 0 | AK10: =AJ10/AI10 -> #DIV/0! | AL10: =SUM(AL6:AL9) -> 0 | AM10: =SUM(AM6:AM9) -> 0 | AN10: =AM10/AL10 -> #DIV/0!
A11: Chiffre d'Affaires (HT) FCFA | B11: =E11+H11+K11+N11+Q11+T11+W11+Z11+AC11+AF11+AI11+AL11 -> 0 | C11: =F11+I11+L11+O11+R11+U11+X11+AA11+AD11+AG11+AJ11+AM11 -> 0 | D11: =C11/B11 -> #DIV/0! | G11: =F11/E11 -> #DIV/0! | J11: =I11/H11 -> #DIV/0! | M11: =L11/K11 -> #DIV/0! | P11: =O11/N11 -> #DIV/0! | S11: =R11/Q11 -> #DIV/0! | V11: =U11/T11 -> #DIV/0! | Y11: =X11/W11 -> #DIV/0! | AB11: =AA11/Z11 -> #DIV/0! | AE11: =AD11/AC11 -> #DIV/0! | AH11: =AG11/AF11 -> #DIV/0! | AK11: =AJ11/AI11 -> #DIV/0! | AN11: =AM11/AL11 -> #DIV/0!
E13: =+E11 -> 0 | F13: =+F11 -> 0 | G13: =F13/E13 -> #DIV/0! | H13: =+H11+E13 -> 0 | I13: =+I11+F13 -> 0 | J13: =I13/H13 -> #DIV/0! | K13: =+K11+H13 -> 0 | L13: =+L11+I13 -> 0 | M13: =L13/K13 -> #DIV/0! | N13: =+N11+K13 -> 0 | O13: =+O11+L13 -> 0 | P13: =O13/N13 -> #DIV/0! | Q13: =+Q11+N13 -> 0 | R13: =+R11+O13 -> 0 | S13: =R13/Q13 -> #DIV/0! | T13: =+T11+Q13 -> 0 | U13: =+U11+R13 -> 0 | V13: =U13/T13 -> #DIV/0! | W13: =+W11+T13 -> 0 | X13: =+X11+U13 -> 0 | Y13: =X13/W13 -> #DIV/0! | Z13: =+Z11+W13 -> 0 | AA13: =+AA11+X13 -> 0 | AB13: =AA13/Z13 -> #DIV/0! | AC13: =+AC11+Z13 -> 0 | AD13: =+AD11+AA13 -> 0 | AE13: =AD13/AC13 -> #DIV/0! | AF13: =+AF11+AC13 -> 0 | AG13: =+AG11+AD13 -> 0 | AH13: =AG13/AF13 -> #DIV/0! | AI13: =+AI11+AF13 -> 0 | AJ13: =+AJ11+AG13 -> 0 | AK13: =AJ13/AI13 -> #DIV/0!

Sheet VISITES CLIENTS
A1: =+SUBTOTAL(3,A3:A1048576) -> 0
A2: DATE | B2: VENDEUR | D2: NOM / PRENOM CLIENT | E2: FONCTION CLIENT | F2: N° TELEPHONE CLIENT | G2: N° WHATSAPP CLIENT | H2: MAIL CLIENT | I2: URL SOCIETE

Sheet ETAT_VENTES
H1: =+SUBTOTAL(3,H3:H1048576) -> 0 | I1: =+SUBTOTAL(9,I3:I1048576) -> 0
A2: DATE | B2: CLIENT | C2: MARQUE | D2: MODÈLE | E2: S/N | F2: GAMME | G2: PAYS | H2: VENDEUR | I2: CA HT | J2: SRC
J72: =IF(B72<>0,1,"-") -> -

Sheet ETAT_CC
H1: =+SUBTOTAL(3,H3:H1048576) -> 0 | I1: =+SUBTOTAL(9,I3:I1048576) -> 0
A2: DATE | B2: CLIENT | C2: MARQUE | D2: MODÈLE | E2: S/N | F2: GAMME | G2: PAYS | H2: VENDEUR | I2: CA HT | K2: PREVISION FACTURATION | L2: N° COMMANDE

Sheet ETAT_CF
B1: =+SUBTOTAL(3,B3:B1048576) -> 0 | F1: =+SUBTOTAL(9,F3:F1048576) -> 0
A2: DATE | B2: N° COMMANDE | C2: MARQUE | D2: MODÈLE | E2: GAMME | F2: PRIX D'ACHAT HT | G2: ETA

Sheet ETAT-Stock
B1: =+SUBTOTAL(3,B3:B1048576) -> 0 | H1: =+SUBTOTAL(9,H3:H1048576) -> 0
A2: STATUT | B2: MARQUE | C2: MODÈLE | D2: S/N | E2: GAMME | F2: PAYS | G2: DATE D'ENTREE EN STOCK | H2: PRIX DE REVIENT HT

Sheet Pipe Opportunité
G1: =SUBTOTAL(3,G3:G476) -> 0 | H1: =SUBTOTAL(9,H3:H476) -> 0
A2: Date | B2: Commercial en charge | C2: Client | D2: Nom du projet | E2: Marques | F2: Modèle | G2: Qté | H2: CA Potentiel | I2: Marge prévisonnelle % | J2: Date de closing prévue | K2: WIN ou LOST | L2: Marque de la concurrence | M2: Modèle de la concurrence | N2: Prix de la concurrence | O2: commentaires
C438: UPCC

Sheet Lost Sales
E1: =SUBTOTAL(3,E3:E182) -> 0 | F1: =SUBTOTAL(9,F3:F182) -> 0
A2: Date | B2: Commercial en charge | C2: Client | D2: Marques | E2: Modèle | F2: CA Potentiel | G2: Marge prévisonnelle % | H2: Marque de la concurrence | I2: Modèle de la concurrence | J2: Prix de la concurrence | K2: commentaires

Sheet EXAMEN SEPT 2025
E1: =SUM(E3:E1048576) -> 0 | F1: =SUM(F3:F1048576) -> 0 | G1: =SUM(G3:G1048576) -> 0 | I1: =SUM(I3:I221) -> 0 | J1: =SUM(J3:J221) -> 0 | K1: =SUM(K3:K221) -> 0 | L1: =SUM(L3:L221) -> 0 | M1: =SUM(M3:M221) -> 0 | N1: =SUM(N3:N221) -> 0 | O1: =SUM(O3:O221) -> 0 | P1: =SUM(P3:P221) -> 0 | ... T1: =SUM(T3:T221) -> 0 | U1: RESULTATS
A2: MARQUES | B2: CATEGORIES | C2: MODELES | E2: STOCK | F2: CF | G2: CC | I2: 45901 | J2: 45870 | K2: 45839 | L2: 45809 | M2: 45778 | N2: 45748 | O2: 45717 | P2: 45689 | Q2: 45658 | R2: 45627 | S2: 45597 | T2: 45566 | U2: VENTES 12 MOIS | V2: A CDER | W2: Délais Fournisseur | X2: Délais Transit | Y2: Délais sécurité | Z2: RETENUE | AA2: COMMENTAIRES | AB2: facturation | AC2: ETA
A3: DIVERS Lift Trucks | B3: ACC. MANUTENTION | C3: 26J-BCB | U3: =SUM(I3:T3) -> 0 | V3: =IF(X3=0,0,(U3/52*(W3+X3+Y3))-E3-F3+G3) -> 0
A4: DIVERS Agri | B4: HARVESTER COMBINE | C4: VERRATO V5 (175Cv) | U4: =SUM(I4:T4) -> 0 | V4: =IF(X4=0,0,(U4/52*(W4+X4+Y4))-E4-F4+G4) -> 0
A5: DIVERS Agri | B5: HARVESTER COMBINE | C5: COMIA C12 | U5: =SUM(I5:T5) -> 0 | V5: =IF(X5=0,0,(U5/52*(W5+X5+Y5))-E5-F5+G5) -> 0
A6: KALMAR | B6: RST | C6: DRU450-62S5 | U6: =SUM(I6:T6) -> 0 | V6: =IF(X6=0,0,(U6/52*(W6+X6+Y6))-E6-F6+G6) -> 0 | W6: 14 | X6: 8 | Y6: 6
A7: KALMAR | B7: ECH | C7: DCU80-45ES7 | U7: =SUM(I7:T7) -> 0 | V7: =IF(X7=0,0,(U7/52*(W7+X7+Y7))-E7-F7+G7) -> 0 | W7: 17 | X7: 8 | Y7: 4
A8: KALMAR | B8: FLT | C8: DCG330-12 | U8: =SUM(I8:T8) -> 0 | V8: =IF(X8=0,0,(U8/52*(W8+X8+Y8))-E8-F8+G8) -> 0 | W8: 24 | X8: 8 | Y8: 4
A9: KALMAR | B9: RST | C9: DRG450-65S5E | U9: =SUM(I9:T9) -> 0 | V9: =IF(X9=0,0,(U9/52*(W9+X9+Y9))-E9-F9+G9) -> 0 | W9: 22 | X9: 8 | Y9: 4
A10: KALMAR | B10: TT | C10: TL2 | U10: =SUM(I10:T10) -> 0 | V10: =IF(X10=0,0,(U10/52*(W10+X10+Y10))-E10-F10+G10) -> 0 | W10: 20 | X10: 8 | Y10: 4
A11: KALMAR | B11: FLT | C11: DCG160-12T | U11: =SUM(I11:T11) -> 0 | V11: =IF(X11=0,0,(U11/52*(W11+X11+Y11))-E11-F11+G11) -> 0 | W11: 22 | X11: 8 | Y11: 4
A12: MANITOU | B12: MXT | C12: 1740P | U12: =SUM(I12:T12) -> 0 | V12: =IF(X12=0,0,(U12/52*(W12+X12+Y12))-E12-F12+G12) -> 0 | W12: 40 | X12: 6 | Y12: 4
A13: MANITOU | B13: M-X | C13: 50-2 | U13: =SUM(I13:T13) -> 0 | V13: =IF(X13=0,0,(U13/52*(W13+X13+Y13))-E13-F13+G13) -> 0 | W13: 40 | X13: 6 | Y13: 4
A14: MANITOU | B14: MC-X | C14: 30-4 | U14: =SUM(I14:T14) -> 0 | V14: =IF(X14=0,0,(U14/52*(W14+X14+Y14))-E14-F14+G14) -> 0 | W14: 45 | X14: 8 | Y14: 4
A15: MANITOU | B15: MI-X | C15: 40G | U15: =SUM(I15:T15) -> 0 | V15: =IF(X15=0,0,(U15/52*(W15+X15+Y15))-E15-F15+G15) -> 0 | W15: 45 | X15: 8 | Y15: 4
A16: MANITOU | B16: MLT-X | C16: 741-140 | U16: =SUM(I16:T16) -> 0 | V16: =IF(X16=0,0,(U16/52*(W16+X16+Y16))-E16-F16+G16) -> 0 | W16: 40 | X16: 6 | Y16: 4
A17: MANITOU | B17: M-X | C17: 50-4 | U17: =SUM(I17:T17) -> 0 | V17: =IF(X17=0,0,(U17/52*(W17+X17+Y17))-E17-F17+G17) -> 0 | W17: 40 | X17: 6 | Y17: 4
... A19: MANITOU | B19: MAN'GO | C19: MAN'GO12 | U19: =SUM(I19:T19) -> 0 | V19: =IF(X19=0,0,(U19/52*(W19+X19+Y19))-E19-F19+G19) -> 0 | W19: 40 | X19: 6 | Y19: 4
A20: MANITOU | B20: ME | C20: 430 | U20: =SUM(I20:T20) -> 0 | V20: =IF(X20=0,0,(U20/52*(W20+X20+Y20))-E20-F20+G20) -> 0 | W20: 20 | X20: 8 | Y20: 4
A21: MANITOU | B21: MT-X | C21: 1440 | U21: =SUM(I21:T21) -> 0 | V21: =IF(X21=0,0,(U21/52*(W21+X21+Y21))-E21-F21+G21) -> 0
A22: MANITOU | B22: EP | C22: 20P EASY | U22: =SUM(I22:T22) -> 0 | V22: =IF(X22=0,0,(U22/52*(W22+X22+Y22))-E22-F22+G22) -> 0
A23: MANITOU | B23: EP | C23: 20 EASY | U23: =SUM(I23:T23) -> 0 | V23: =IF(X23=0,0,(U23/52*(W23+X23+Y23))-E23-F23+G23) -> 0 | W23: 16 | X23: 4 | Y23: 4
A24: MANITOU | B24: MI-X | C24: 25D | U24: =SUM(I24:T24) -> 0 | V24: =IF(X24=0,0,(U24/52*(W24+X24+Y24))-E24-F24+G24) -> 0 | W24: 20 | X24: 8 | Y24: 4
A25: MANITOU | B25: ATJ | C25: 160ATJ+ RC | U25: =SUM(I25:T25) -> 0 | V25: =IF(X25=0,0,(U25/52*(W25+X25+Y25))-E25-F25+G25) -> 0
A26: MANITOU | B26: ER | C26: 20 | U26: =SUM(I26:T26) -> 0 | V26: =IF(X26=0,0,(U26/52*(W26+X26+Y26))-E26-F26+G26) -> 0 | W26: 20 | X26: 8 | Y26: 4
A27: MANITOU | B27: ATJ | C27: 160ATJ | U27: =SUM(I27:T27) -> 0 | V27: =IF(X27=0,0,(U27/52*(W27+X27+Y27))-E27-F27+G27) -> 0
A28: MANITOU | B28: ATJ | C28: 180ATJ | U28: =SUM(I28:T28) -> 0 | V28: =IF(X28=0,0,(U28/52*(W28+X28+Y28))-E28-F28+G28) -> 0
A29: MANITOU | B29: ATJ | C29: 200ATJ | U29: =SUM(I29:T29) -> 0 | V29: =IF(X29=0,0,(U29/52*(W29+X29+Y29))-E29-F29+G29) -> 0
A30: MANITOU | B30: EP | C30: 15 EASY | U30: =SUM(I30:T30) -> 0 | V30: =IF(X30=0,0,(U30/52*(W30+X30+Y30))-E30-F30+G30) -> 0 | W30: 20 | X30: 8 | Y30: 4
A31: MANITOU | B31: EP | C31: 16 EASY | U31: =SUM(I31:T31) -> 0 | V31: =IF(X31=0,0,(U31/52*(W31+X31+Y31))-E31-F31+G31) -> 0
A32: MANITOU | B32: ER | C32: 14 | U32: =SUM(I32:T32) -> 0 | V32: =IF(X32=0,0,(U32/52*(W32+X32+Y32))-E32-F32+G32) -> 0
A33: MANITOU | B33: ER | C33: 16 | U33: =SUM(I33:T33) -> 0 | V33: =IF(X33=0,0,(U33/52*(W33+X33+Y33))-E33-F33+G33) -> 0
A34: MANITOU | B34: ES | C34: 412 | U34: =SUM(I34:T34) -> 0 | V34: =IF(X34=0,0,(U34/52*(W34+X34+Y34))-E34-F34+G34) -> 0
A35: MANITOU | B35: ES | C35: 616 | U35: =SUM(I35:T35) -> 0 | V35: =IF(X35=0,0,(U35/52*(W35+X35+Y35))-E35-F35+G35) -> 0
A36: MANITOU | B36: ES | C36: 720 | U36: =SUM(I36:T36) -> 0 | V36: =IF(X36=0,0,(U36/52*(W36+X36+Y36))-E36-F36+G36) -> 0
A37: MANITOU | B37: ES | C37: 820 | U37: =SUM(I37:T37) -> 0 | V37: =IF(X37=0,0,(U37/52*(W37+X37+Y37))-E37-F37+G37) -> 0
A38: MANITOU | B38: MC-X | C38: 30-2 | U38: =SUM(I38:T38) -> 0 | V38: =IF(X38=0,0,(U38/52*(W38+X38+Y38))-E38-F38+G38) -> 0
A39: MANITOU | B39: ME | C39: 320 | U39: =SUM(I39:T39) -> 0 | V39: =IF(X39=0,0,(U39/52*(W39+X39+Y39))-E39-F39+G39) -> 0
A40: MANITOU | B40: ME | C40: 435 | U40: =SUM(I40:T40) -> 0 | V40: =IF(X40=0,0,(U40/52*(W40+X40+Y40))-E40-F40+G40) -> 0
A41: MANITOU | B41: ME | C41: 440 | U41: =SUM(I41:T41) -> 0 | V41: =IF(X41=0,0,(U41/52*(W41+X41+Y41))-E41-F41+G41) -> 0
A42: MANITOU | B42: ME | C42: 450 | U42: =SUM(I42:T42) -> 0 | V42: =IF(X42=0,0,(U42/52*(W42+X42+Y42))-E42-F42+G42) -> 0
... A45: MANITOU | B45: MHT-X | C45: 790 | U45: =SUM(I45:T45) -> 0 | V45: =IF(X45=0,0,(U45/52*(W45+X45+Y45))-E45-F45+G45) -> 0
A46: MANITOU | B46: MHT-X | C46: 10135 | U46: =SUM(I46:T46) -> 0 | V46: =IF(X46=0,0,(U46/52*(W46+X46+Y46))-E46-F46+G46) -> 0
A47: MANITOU | B47: MHT-X | C47: 10160 | U47: =SUM(I47:T47) -> 0 | V47: =IF(X47=0,0,(U47/52*(W47+X47+Y47))-E47-F47+G47) -> 0
A48: MANITOU | B48: MHT-X | C48: 790 MINING | U48: =SUM(I48:T48) -> 0 | V48: =IF(X48=0,0,(U48/52*(W48+X48+Y48))-E48-F48+G48) -> 0
A49: MANITOU | B49: MI-X | C49: 15D | U49: =SUM(I49:T49) -> 0 | V49: =IF(X49=0,0,(U49/52*(W49+X49+Y49))-E49-F49+G49) -> 0
A50: MANITOU | B50: MI-X | C50: 15G | U50: =SUM(I50:T50) -> 0 | V50: =IF(X50=0,0,(U50/52*(W50+X50+Y50))-E50-F50+G50) -> 0
A51: MANITOU | B51: MI-X | C51: 20D | U51: =SUM(I51:T51) -> 0 | V51: =IF(X51=0,0,(U51/52*(W51+X51+Y51))-E51-F51+G51) -> 0
A52: MANITOU | B52: MI-X | C52: 20G | U52: =SUM(I52:T52) -> 0 | V52: =IF(X52=0,0,(U52/52*(W52+X52+Y52))-E52-F52+G52) -> 0
A53: MANITOU | B53: MI-X | C53: 25G | U53: =SUM(I53:T53) -> 0 | V53: =IF(X53=0,0,(U53/52*(W53+X53+Y53))-E53-F53+G53) -> 0
A54: MANITOU | B54: MI-X | C54: 30G | U54: =SUM(I54:T54) -> 0 | V54: =IF(X54=0,0,(U54/52*(W54+X54+Y54))-E54-F54+G54) -> 0 | W54: 45 | X54: 8 | Y54: 4
A55: MANITOU | B55: MI-X | C55: 35G | U55: =SUM(I55:T55) -> 0 | V55: =IF(X55=0,0,(U55/52*(W55+X55+Y55))-E55-F55+G55) -> 0
A56: MANITOU | B56: MI-X | C56: 45D | U56: =SUM(I56:T56) -> 0 | V56: =IF(X56=0,0,(U56/52*(W56+X56+Y56))-E56-F56+G56) -> 0
A57: MANITOU | B57: MI-X | C57: 45G | U57: =SUM(I57:T57) -> 0 | V57: =IF(X57=0,0,(U57/52*(W57+X57+Y57))-E57-F57+G57) -> 0
A58: MANITOU | B58: MI-X | C58: 50G | U58: =SUM(I58:T58) -> 0 | V58: =IF(X58=0,0,(U58/52*(W58+X58+Y58))-E58-F58+G58) -> 0
A59: MANITOU | B59: MI-X | C59: 50LD | U59: =SUM(I59:T59) -> 0 | V59: =IF(X59=0,0,(U59/52*(W59+X59+Y59))-E59-F59+G59) -> 0
A60: MANITOU | B60: MI-X | C60: 50LG | U60: =SUM(I60:T60) -> 0 | V60: =IF(X60=0,0,(U60/52*(W60+X60+Y60))-E60-F60+G60) -> 0
A61: MANITOU | B61: MI-X | C61: 60D | U61: =SUM(I61:T61) -> 0 | V61: =IF(X61=0,0,(U61/52*(W61+X61+Y61))-E61-F61+G61) -> 0
A62: MANITOU | B62: MI-X | C62: 60G | U62: =SUM(I62:T62) -> 0 | V62: =IF(X62=0,0,(U62/52*(W62+X62+Y62))-E62-F62+G62) -> 0
A63: MANITOU | B63: MI-X | C63: 70G | U63: =SUM(I63:T63) -> 0 | V63: =IF(X63=0,0,(U63/52*(W63+X63+Y63))-E63-F63+G63) -> 0
A64: MANITOU | B64: MLT-X | C64: 845 | U64: =SUM(I64:T64) -> 0 | V64: =IF(X64=0,0,(U64/52*(W64+X64+Y64))-E64-F64+G64) -> 0 | W64: 40 | X64: 6 | Y64: 4
A65: MANITOU | B65: MLT-X | C65: 850 | U65: =SUM(I65:T65) -> 0 | V65: =IF(X65=0,0,(U65/52*(W65+X65+Y65))-E65-F65+G65) -> 0
A66: MANITOU | B66: MLT-X | C66: 1035 LT LSU | U66: =SUM(I66:T66) -> 0 | V66: =IF(X66=0,0,(U66/52*(W66+X66+Y66))-E66-F66+G66) -> 0 | W66: 40 | X66: 6 | Y66: 4
A67: MANITOU | B67: MLT-X | C67: 732-120 | U67: =SUM(I67:T67) -> 0 | V67: =IF(X67=0,0,(U67/52*(W67+X67+Y67))-E67-F67+G67) -> 0 | W67: 40 | X67: 6 | Y67: 4
A68: MANITOU | B68: MLT-X | C68: 735 T LSU | U68: =SUM(I68:T68) -> 0 | V68: =IF(X68=0,0,(U68/52*(W68+X68+Y68))-E68-F68+G68) -> 0 | W68: 40 | X68: 6 | Y68: 4
A69: MANITOU | B69: MLT-X NewAg | C69: 737-130 PS+ CAB A/C | U69: =SUM(I69:T69) -> 0 | V69: =IF(X69=0,0,(U69/52*(W69+X69+Y69))-E69-F69+G69) -> 0 | W69: 40 | X69: 6 | Y69: 4
A70: MANITOU | B70: MLT-X NewAg | C70: 741-140 V+ | U70: =SUM(I70:T70) -> 0 | V70: =IF(X70=0,0,(U70/52*(W70+X70+Y70))-E70-F70+G70) -> 0 | W70: 40 | X70: 6 | Y70: 4
A71: MANITOU | B71: MLT-X NewAg XL | C71: 1041-145 PS+L | U71: =SUM(I71:T71) -> 0 | V71: =IF(X71=0,0,(U71/52*(W71+X71+Y71))-E71-F71+G71) -> 0 | W71: 40 | X71: 6 | Y71: 4
A72: MANITOU | B72: MLT-X NewAg XL | C72: 841-145 PS+ | U72: =SUM(I72:T72) -> 0 | V72: =IF(X72=0,0,(U72/52*(W72+X72+Y72))-E72-F72+G72) -> 0 | W72: 40 | X72: 6 | Y72: 4
A73: MANITOU | B73: MLT-X NewAg XL | C73: 961-160 V+ L | U73: =SUM(I73:T73) -> 0 | V73: =IF(X73=0,0,(U73/52*(W73+X73+Y73))-E73-F73+G73) -> 0 | W73: 40 | X73: 6 | Y73: 4
A74: MANITOU | B74: MRT-X | C74: 1645 | U74: =SUM(I74:T74) -> 0 | V74: =IF(X74=0,0,(U74/52*(W74+X74+Y74))-E74-F74+G74) -> 0
A75: MANITOU | B75: MRT-X | C75: 1845 | U75: =SUM(I75:T75) -> 0 | V75: =IF(X75=0,0,(U75/52*(W75+X75+Y75))-E75-F75+G75) -> 0
A76: MANITOU | B76: MRT-X | C76: 2145 | U76: =SUM(I76:T76) -> 0 | V76: =IF(X76=0,0,(U76/52*(W76+X76+Y76))-E76-F76+G76) -> 0
A77: MANITOU | B77: MRT-X | C77: 2550 | U77: =SUM(I77:T77) -> 0 | V77: =IF(X77=0,0,(U77/52*(W77+X77+Y77))-E77-F77+G77) -> 0
A78: MANITOU | B78: MRT-X | C78: 2650 | U78: =SUM(I78:T78) -> 0 | V78: =IF(X78=0,0,(U78/52*(W78+X78+Y78))-E78-F78+G78) -> 0
A79: MANITOU | B79: MRT-X | C79: 2660 | U79: =SUM(I79:T79) -> 0 | V79: =IF(X79=0,0,(U79/52*(W79+X79+Y79))-E79-F79+G79) -> 0
A80: MANITOU | B80: MRT-X | C80: 3060 | U80: =SUM(I80:T80) -> 0 | V80: =IF(X80=0,0,(U80/52*(W80+X80+Y80))-E80-F80+G80) -> 0
A81: MANITOU | B81: MRT-X | C81: 3570 | U81: =SUM(I81:T81) -> 0 | V81: =IF(X81=0,0,(U81/52*(W81+X81+Y81))-E81-F81+G81) -> 0
A82: MANITOU | B82: MRT-X | C82: 3570ES | U82: =SUM(I82:T82) -> 0 | V82: =IF(X82=0,0,(U82/52*(W82+X82+Y82))-E82-F82+G82) -> 0
A83: MANITOU | B83: MSI | C83: 20T | U83: =SUM(I83:T83) -> 0 | V83: =IF(X83=0,0,(U83/52*(W83+X83+Y83))-E83-F83+G83) -> 0
A84: MANITOU | B84: MSI | C84: 25T | U84: =SUM(I84:T84) -> 0 | V84: =IF(X84=0,0,(U84/52*(W84+X84+Y84))-E84-F84+G84) -> 0
A85: MANITOU | B85: MSI | C85: 30T | U85: =SUM(I85:T85) -> 0 | V85: =IF(X85=0,0,(U85/52*(W85+X85+Y85))-E85-F85+G85) -> 0
A86: MANITOU | B86: MSI | C86: 35T | U86: =SUM(I86:T86) -> 0 | V86: =IF(X86=0,0,(U86/52*(W86+X86+Y86))-E86-F86+G86) -> 0
A87: MANITOU | B87: MSI | C87: 40T | U87: =SUM(I87:T87) -> 0 | V87: =IF(X87=0,0,(U87/52*(W87+X87+Y87))-E87-F87+G87) -> 0
A88: MANITOU | B88: MSI | C88: 50T | U88: =SUM(I88:T88) -> 0 | V88: =IF(X88=0,0,(U88/52*(W88+X88+Y88))-E88-F88+G88) -> 0
A89: MANITOU | B89: MT-X | C89: 625 | U89: =SUM(I89:T89) -> 0 | V89: =IF(X89=0,0,(U89/52*(W89+X89+Y89))-E89-F89+G89) -> 0
A90: MANITOU | B90: MT-X | C90: 733 | U90: =SUM(I90:T90) -> 0 | V90: =IF(X90=0,0,(U90/52*(W90+X90+Y90))-E90-F90+G90) -> 0
A91: MANITOU | B91: MT-X | C91: 1030 | U91: =SUM(I91:T91) -> 0 | V91: =IF(X91=0,0,(U91/52*(W91+X91+Y91))-E91-F91+G91) -> 0
A92: MANITOU | B92: MT-X | C92: 1840 | U92: =SUM(I92:T92) -> 0 | V92: =IF(X92=0,0,(U92/52*(W92+X92+Y92))-E92-F92+G92) -> 0
A93: MANITOU | B93: MT-X | C93: 1030 MINING | U93: =SUM(I93:T93) -> 0 | V93: =IF(X93=0,0,(U93/52*(W93+X93+Y93))-E93-F93+G93) -> 0
A94: MANITOU | B94: MT-X | C94: 1440A | U94: =SUM(I94:T94) -> 0 | V94: =IF(X94=0,0,(U94/52*(W94+X94+Y94))-E94-F94+G94) -> 0
A95: MANITOU | B95: MT-X | C95: 1840A | U95: =SUM(I95:T95) -> 0 | V95: =IF(X95=0,0,(U95/52*(W95+X95+Y95))-E95-F95+G95) -> 0
A96: MANITOU | B96: MT-X | C96: 733 MINING | U96: =SUM(I96:T96) -> 0 | V96: =IF(X96=0,0,(U96/52*(W96+X96+Y96))-E96-F96+G96) -> 0
A97: MANITOU | B97: M-X | C97: 30.4 | U97: =SUM(I97:T97) -> 0 | V97: =IF(X97=0,0,(U97/52*(W97+X97+Y97))-E97-F97+G97) -> 0 | W97: 40 | X97: 6 | Y97: 4
A98: MANITOU | B98: M-X | C98: 30-2 | U98: =SUM(I98:T98) -> 0 | V98: =IF(X98=0,0,(U98/52*(W98+X98+Y98))-E98-F98+G98) -> 0 | W98: 40 | X98: 6 | Y98: 4
A99: MANITOU | B99: M-X | C99: 70-2 | U99: =SUM(I99:T99) -> 0 | V99: =IF(X99=0,0,(U99/52*(W99+X99+Y99))-E99-F99+G99) -> 0
A100: MANITOU | B100: TJ | C100: 220TJ | U100: =SUM(I100:T100) -> 0 | V100: =IF(X100=0,0,(U100/52*(W100+X100+Y100))-E100-F100+G100) -> 0
A101: MANITOU | B101: TJ | C101: 280TJ | U101: =SUM(I101:T101) -> 0 | V101: =IF(X101=0,0,(U101/52*(W101+X101+Y101))-E101-F101+G101) -> 0
A102: MANITOU | B102: MI-X | C102: 50D | U102: =SUM(I102:T102) -> 0 | V102: =IF(X102=0,0,(U102/52*(W102+X102+Y102))-E102-F102+G102) -> 0 | W102: 21 | X102: 8 | Y102: 4
A103: MANITOU | B103: MI-X | C103: 30D | U103: =SUM(I103:T103) -> 0 | V103: =IF(X103=0,0,(U103/52*(W103+X103+Y103))-E103-F103+G103) -> 0 | W103: 20 | X103: 8 | Y103: 4
...

Sheet SN
A1: 123456

Sheet FORECAST
A1: TAE | L1: CONSTRAINED FORECAST 2026
D3: 2017 | E3: 2018 | F3: 2019 | G3: 2020 | H3: 2021 | I3: 2022 | J3: 2023 | K3: 2024 | L3: Jan | M3: Fev | N3: Mar | O3: Avr | P3: Mai | Q3: Jui | R3: Juil | S3: Aou | T3: Sep | U3: Oct | V3: Nov | W3: Dec | X3: Sous total 2026
L4: STU Con | M4: STU Con | N4: STU Con | O4: STU Con | P4: STU Con | Q4: STU Con | R4: STU Con | S4: STU Con | T4: STU Con | U4: STU Con | V4: STU Con | W4: STU Con
A5: All Sales Models | D5: 0 | E5: 17 | F5: 58 | G5: 30 | H5: 66 | I5: 64 | J5: 32 | K5: 45 | L5: =L248+L421+L501 -> 0 | M5: =M248+M421+M501 -> 0 | N5: =N248+N421+N501 -> 0 | O5: =O248+O421+O501 -> 0 | P5: =P248+P421+P501 -> 0 | Q5: =Q248+Q421+Q501 -> 0 | R5: =R248+R421+R501 -> 0 | S5: =S248+S421+S501 -> 0 | ... X5: =X248+X421+X501 -> 0
A6: ME | B6: 315C TLL48 24V | X6: =SUM(L6:W6) -> 0
A7: ME | B7: 315 TLL45 48V | X7: =SUM(L7:W7) -> 0
A8: ME | B8: 316 TLL50 48V | X8: =SUM(L8:W8) -> 0
A9: ME | B9: 318 TLL50 48V | X9: =SUM(L9:W9) -> 0
A10: ME | B10: 320 TLL50 48V | X10: =SUM(L10:W10) -> 0
A11: ME | B11: 418 | X11: =SUM(L11:W11) -> 0
A12: ME | B12: 420 TLL50 48V | X12: =SUM(L12:W12) -> 0
A13: ME | B13: 425C TLL50 48V | I13: 4 | X13: =SUM(L13:W13) -> 0
A14: ME | B14: 425 TLL48 80V | F14: 2 | H14: 11 | K14: 1 | X14: =SUM(L14:W14) -> 0
A15: ME | B15: 430 TLL48 80V | K15: 2 | X15: =SUM(L15:W15) -> 0
A16: ME | B16: 435 TLL43 80V | X16: =SUM(L16:W16) -> 0
A17: ME | B17: 440 | X17: =SUM(L17:W17) -> 0
A18: ME | B18: 445 | X18: =SUM(L18:W18) -> 0
A19: ME | B19: 450 | X19: =SUM(L19:W19) -> 0
A20: MI-X | B20: 15D | X20: =SUM(L20:W20) -> 0
A21: MI-X | B21: 15G | X21: =SUM(L21:W21) -> 0
A22: MI-X | B22: 18D TLL47 | F22: 1 | H22: 2 | I22: 3 | K22: 2 | X22: =SUM(L22:W22) -> 0
A23: MI-X | B23: 18G | F23: 1 | H23: 2 | X23: =SUM(L23:W23) -> 0
A24: MI-X | B24: 20D | X24: =SUM(L24:W24) -> 0
A25: MI-X | B25: 20G | X25: =SUM(L25:W25) -> 0
A26: MI-X | B26: 25D TLL47 | H26: 1 | I26: 4 | J26: 1 | K26: 2 | X26: =SUM(L26:W26) -> 0
A27: MI-X | B27: 25G | X27: =SUM(L27:W27) -> 0
A28: MI-X | B28: 30D TLL47 | F28: 9 | G28: 8 | H28: 17 | I28: 17 | J28: 9 | K28: 8 | X28: =SUM(L28:W28) -> 0
A29: MI-X | B29: 30D DLL33 | X29: =SUM(L29:W29) -> 0
A30: MI-X | B30: 30G | F30: 1 | I30: 1 | J30: 1 | X30: =SUM(L30:W30) -> 0
A31: MI-X | B31: 35D TLL47 | H31: 2 | J31: 2 | K31: 1 | X31: =SUM(L31:W31) -> 0
A32: MI-X | B32: 35G | X32: =SUM(L32:W32) -> 0
A33: MI-X | B33: 40D DLL30 | X33: =SUM(L33:W33) -> 0
A34: MI-X | B34: 40D DVT33 | F34: 1 | G34: 2 | H34: 2 | I34: 6 | J34: 2 | K34: 5 | X34: =SUM(L34:W34) -> 0
A35: MI-X | B35: 40G | G35: 2 | H35: 1 | K35: 3 | X35: =SUM(L35:W35) -> 0
A36: MI-X | B36: 45D | X36: =SUM(L36:W36) -> 0
A37: MI-X | B37: 45G | X37: =SUM(L37:W37) -> 0
A38: MI-X | B38: 50D DLL30 | X38: =SUM(L38:W38) -> 0
A39: MI-X | B39: 50D TLL45 | E39: 1 | F39: 2 | G39: 1 | H39: 2 | I39: 2 | J39: 1 | K39: 1 | X39: =SUM(L39:W39) -> 0
A40: MI-X | B40: 50G | X40: =SUM(L40:W40) -> 0
A41: MI-X | B41: 50LD | X41: =SUM(L41:W41) -> 0
A42: MI-X | B42: 50LG | X42: =SUM(L42:W42) -> 0
A43: MI-X | B43: 60D | X43: =SUM(L43:W43) -> 0
A44: MI-X | B44: 60G | X44: =SUM(L44:W44) -> 0
A45: MI-X | B45: 70D DLL33 | X45: =SUM(L45:W45) -> 0
A46: MI-X | B46: 70D DLL3 | X46: =SUM(L46:W46) -> 0
A47: MI-X | B47: 70D TLL45 | F47: 1 | H47: 1 | I47: 5 | X47: =SUM(L47:W47) -> 0
A48: MI-X | B48: 70G | X48: =SUM(L48:W48) -> 0
A49: MI-X | B49: 80D | X49: =SUM(L49:W49) -> 0
A50: MI-X | B50: 100D DVT33 | X50: =SUM(L50:W50) -> 0
A51: MI-X | B51: 100D TLL50 CAB A/C | X51: =SUM(L51:W51) -> 0
A52: MSI | B52: 25T | X52: =SUM(L52:W52) -> 0
A53: MSI | B53: 30T | X53: =SUM(L53:W53) -> 0
A54: MSI | B54: 35T | X54: =SUM(L54:W54) -> 0
A55: MSI | B55: 40T | X55: =SUM(L55:W55) -> 0
A56: MSI | B56: 50T | X56: =SUM(L56:W56) -> 0
A57: M-X | B57: 30-2 | I57: 3 | X57: =SUM(L57:W57) -> 0
A58: M-X | B58: 30-4 DVT37 CAB A/C | F58: 2 | G58: 1 | X58: =SUM(L58:W58) -> 0
A59: M-X | B59: 50-2 DVT37 | E59: 7 | F59: 9 | G59: 4 | H59: 6 | I59: 9 | J59: 6 | K59: 8 | X59: =SUM(L59:W59) -> 0
A60: M-X | B60: 50-2 TLL45 | X60: =SUM(L60:W60) -> 0
A61: M-X | B61: 50-4 TLL45 CAB A/C | X61: =SUM(L61:W61) -> 0
A62: M-X | B62: 50-4 DVT37 | E62: 3 | F62: 2 | H62: 2 | I62: 1 | J62: 1 | K62: 2 | X62: =SUM(L62:W62) -> 0
A63: M-X | B63: 70 | X63: =SUM(L63:W63) -> 0
A64: MC-X | B64: 18-2 | X64: =SUM(L64:W64) -> 0
A65: MC-X | B65: 18-4 | X65: =SUM(L65:W65) -> 0
A66: MC-X | B66: 25-2 | X66: =SUM(L66:W66) -> 0
A67: MC-X | B67: 25-4 | X67: =SUM(L67:W67) -> 0
A68: MC-X | B68: 30-2 | X68: =SUM(L68:W68) -> 0
A69: MC-X | B69: 30-4 TLL40 CAB A/C | X69: =SUM(L69:W69) -> 0
A70: CHARIOTS ELEVATEUR | D70: 0 | E70: 11 | F70: 31 | G70: 18 | H70: 49 | I70: 55 | J70: 23 | K70: 35 | L70: =SUM(L6:L65) -> 0 | M70: =SUM(M6:M65) -> 0 | N70: =SUM(N6:N65) -> 0 | O70: =SUM(O6:O65) -> 0 | P70: =SUM(P6:P65) -> 0 | Q70: =SUM(Q6:Q65) -> 0 | R70: =SUM(R6:R65) -> 0 | S70: =SUM(S6:S65) -> 0 | ... W70: =SUM(W6:W65) -> 0 | X70: =SUM(X6:X69) -> 0
A71: TMM | B71: 20 | X71: =SUM(L71:W71) -> 0
A72: TMM | B72: 20-4W | X72: =SUM(L72:W72) -> 0
A73: TMM | B73: 25 | X73: =SUM(L73:W73) -> 0
A74: TMM | B74: 25-4W | X74: =SUM(L74:W74) -> 0
A75: TMT | B75: 25I | X75: =SUM(L75:W75) -> 0
A76: TMT | B76: 25S | X76: =SUM(L76:W76) -> 0
A77: TMT | B77: 25P | X77: =SUM(L77:W77) -> 0
A78: TMT | B78: 27S | X78: =SUM(L78:W78) -> 0
A79: TMT | B79: 27P | X79: =SUM(L79:W79) -> 0
A80: TMM/TMT | D80: 0 | E80: 0 | F80: 0 | G80: 0 | H80: 0 | I80: 0 | J80: 0 | K80: 0 | L80: =SUM(L71:L79) -> 0 | M80: =SUM(M71:M79) -> 0 | N80: =SUM(N71:N79) -> 0 | O80: =SUM(O71:O79) -> 0 | P80: =SUM(P71:P79) -> 0 | Q80: =SUM(Q71:Q79) -> 0 | R80: =SUM(R71:R79) -> 0 | S80: =SUM(S71:S79) -> 0 | ... X80: =SUM(X71:X79) -> 0
A81: EMA II | B81: 13 | X81: =SUM(L81:W81) -> 0
A82: EMA II | B82: 17 | X82: =SUM(L82:W82) -> 0
A83: EMA II | B83: 18 HL-1 | X83: =SUM(L83:W83) -> 0
A84: EMA II | B84: 18 HL-2 | X84: =SUM(L84:W84) -> 0
A85: EMA II | B85: 20 | X85: =SUM(L85:W85) -> 0
A86: EMA II | B86: 20 HD-1 | X86: =SUM(L86:W86) -> 0
A87: EMA II | B87: 20 HD-2 | X87: =SUM(L87:W87) -> 0
A88: ER | B88: 12 | X88: =SUM(L88:W88) -> 0
A89: ER | B89: 14 | X89: =SUM(L89:W89) -> 0
A90: ER | B90: 16 | X90: =SUM(L90:W90) -> 0
A91: ER | B91: 16 HD | X91: =SUM(L91:W91) -> 0
A92: ER | B92: 20 | X92: =SUM(L92:W92) -> 0
A93: ER | B93: 20 HD | K93: 1 | X93: =SUM(L93:W93) -> 0
A94: STACKY | B94: 10 | X94: =SUM(L94:W94) -> 0
A95: STACKY | B95: 14 | X95: =SUM(L95:W95) -> 0
A96: KLEOS | B96: DMH | X96: =SUM(L96:W96) -> 0
A97: KLEOS | B97: HM | X97: =SUM(L97:W97) -> 0
A98: KLEOS | B98: EB | X98: =SUM(L98:W98) -> 0
A99: CI | B99: 10LC | X99: =SUM(L99:W99) -> 0
A100: CI | B100: 12PF | X100: =SUM(L100:W100) -> 0
A101: CI | B101: 20 | X101: =SUM(L101:W101) -> 0
...

Sheet Plan d'action
A1: DATE | B1: ACTIONS | C1: NIVEAU DE PRIORITE | D1: RESPONSABLE | E1: DATE DE FIN PREVUE | F1: STATUT | I1: COMMENTAIRES
F2: EN COURS | G2: RETARD | H2: TERMINE
F3: FALSE | G3: FALSE | H3: FALSE
F4: FALSE | G4: FALSE | H4: FALSE
F5: FALSE | G5: FALSE | H5: FALSE
F6: FALSE | G6: FALSE | H6: FALSE
F7: FALSE | G7: FALSE | H7: FALSE
F8: FALSE | G8: FALSE | H8: FALSE
F9: FALSE | G9: FALSE | H9: FALSE
F10: FALSE | G10: FALSE | H10: FALSE
F11: FALSE | G11: FALSE | H11: FALSE
F12: FALSE | G12: FALSE | H12: FALSE

Sheet LISTE
A1: MARQUE | B1: MODÈLE | C1: GAMME | D1: PAYS | E1: VENDEUR | F1: SRC | G1: STATUT | H1: NIVEAU DE PRIORITE | I1: STATUT
A2: MANITOU | B2: ME315C | C2: MF 300 | D2: CAMEROUN | E2: Y. MOUSSONG | F2: 1 | G2: ABANDONNE | H2: Elevé | I2: MCR (Machine en Cours de Route)
A3: KALMAR | B3: ME315 | C3: MF GLOBAL SERIES | D3: CENTRAFRIQUE | E3: D. SIAKA | F3: 0 | G3: EN COURS | H3: Moyenne | I3: IM4 TTC (Dédouané)
A4: MASSEY FERGUSON | B4: ME316 | C4: MF BEAUVAIS SERIES | D4: GUINEE EQUATORIALE | E4: G. WAFO | G4: REPORTE | H4: Faible | I4: IM7 HT (Sous Douane)
A5: NARDI | B5: ME318 | C5: HARVESTER COMBINE | D5: TCHAD | E5: A. MAGWETH | G5: GAGNE | H5: Optionnelle
A6: DIVERS Lift Trucks | B6: ME320 | C6: ACC. AGRICOLE | D6: GABON | E6: P. DEBANTEL | G6: PERDU
A7: DIVERS Agri | B7: ME418 | C7: ACC. MANUTENTION | D7: CONGO | E7: P. PIERRES
A8: PARTS | B8: ME420 | C8: MI/ME | D8: RDC NORD | E8: F. ALBERT-THENET
A9: USED | B9: ME425C | C9: EP/ES/ER/EMA | D9: RDC SUD | E9: S. DOUMBOUYA
B10: ME425 | C10: MC/M | D10: RWANDA | E10: P. LAVICTOIRE
B11: ME430 | C11: MSI | D11: BURUNDI | E11: S. NDJOUBY
B12: ME435 | C12: MWEP | D12: MAROC TH | E12: F. MAKON
B13: ME440 | C13: MXT/MT/MLT/MHT/MRT | D13: MAROC IND. | E13: C. ZAMBO
B14: ME445 | C14: FLT | D14: MAROC MINING
B15: ME450 | C15: ECH | D15: CÔTE D'IVOIRE
B16: MI-X15D | C16: RST | D16: MALI
B17: MI-X15G | C17: TT | D17: BURKINA FASO
B18: MI-X18D | C18: TRANSPALETTE MANUEL | D18: NIGER
B19: MI-X18G | D19: LYBIE
B20: MI-X20D | D20: MAURITANIE
B21: MI-X20G
B22: MI-X25D
B23: MI-X25G
B24: MI-X30D
B25: MI-X30G
B26: MI-X35D
B27: MI-X35G
B28: MI-X40D
B29: MI-X40G
B30: MI-X45D
B31: MI-X45G
B32: MI-X50D
... B472: SOYA ADAPTATOR
